{
  "1132114023_1": [
    {
      "tile": {
        "sheet": 38,
        "col": 0,
        "row": 8
      },
      "x": 91,
      "y": 1
    },
    {
      "tile": {
        "sheet": 38,
        "col": 4,
        "row": 4
      },
      "x": 92,
      "y": 5
    },
    {
      "tile": {
        "sheet": 38,
        "col": 4,
        "row": 4
      },
      "x": 39,
      "y": 54
    },
    {
      "tile": {
        "sheet": 38,
        "col": 2,
        "row": 8
      },
      "x": 105,
      "y": 72
    },
    {
      "tile": {
        "sheet": 38,
        "col": 0,
        "row": 11
      },
      "x": 8,
      "y": 17
    },
    {
      "tile": {
        "sheet": 38,
        "col": 0,
        "row": 8
      },
      "x": 96,
      "y": 1
    },
    {
      "tile": {
        "sheet": 38,
        "col": 4,
        "row": 4
      },
      "x": 91,
      "y": 34
    },
    {
      "tile": {
        "sheet": 38,
        "col": 3,
        "row": 3
      },
      "x": 4,
      "y": 69
    },
    {
      "tile": {
        "sheet": 38,
        "col": 0,
        "row": 8
      },
      "x": 12,
      "y": 29
    },
    {
      "tile": {
        "sheet": 38,
        "col": 2,
        "row": 8
      },
      "x": 25,
      "y": 16
    },
    {
      "tile": {
        "sheet": 38,
        "col": 0,
        "row": 8
      },
      "x": 45,
      "y": 43
    },
    {
      "tile": {
        "sheet": 38,
        "col": 2,
        "row": 8
      },
      "x": 42,
      "y": 4
    },
    {
      "tile": {
        "sheet": 38,
        "col": 4,
        "row": 4
      },
      "x": 92,
      "y": 2
    },
    {
      "tile": {
        "sheet": 38,
        "col": 3,
        "row": 3
      },
      "x": 60,
      "y": 59
    },
    {
      "tile": {
        "sheet": 38,
        "col": 5,
        "row": 9
      },
      "x": 110,
      "y": 57
    },
    {
      "tile": {
        "sheet": 38,
        "col": 4,
        "row": 4
      },
      "x": 93,
      "y": 2
    },
    {
      "tile": {
        "sheet": 38,
        "col": 0,
        "row": 11
      },
      "x": 5,
      "y": 17
    },
    {
      "tile": {
        "sheet": 38,
        "col": 4,
        "row": 4
      },
      "x": 91,
      "y": 31
    },
    {
      "tile": {
        "sheet": 38,
        "col": 2,
        "row": 8
      },
      "x": 28,
      "y": 16
    },
    {
      "tile": {
        "sheet": 38,
        "col": 5,
        "row": 9
      },
      "x": 113,
      "y": 5
    },
    {
      "tile": {
        "sheet": 38,
        "col": 4,
        "row": 4
      },
      "x": 94,
      "y": 2
    },
    {
      "tile": {
        "sheet": 38,
        "col": 0,
        "row": 3
      },
      "x": 61,
      "y": 16
    },
    {
      "tile": {
        "sheet": 38,
        "col": 0,
        "row": 8
      },
      "x": 115,
      "y": 14
    },
    {
      "tile": {
        "sheet": 38,
        "col": 0,
        "row": 8
      },
      "x": 75,
      "y": 22
    },
    {
      "tile": {
        "sheet": 38,
        "col": 4,
        "row": 4
      },
      "x": 95,
      "y": 2
    },
    {
      "tile": {
        "sheet": 38,
        "col": 0,
        "row": 8
      },
      "x": 26,
      "y": 42
    },
    {
      "tile": {
        "sheet": 38,
        "col": 4,
        "row": 4
      },
      "x": 93,
      "y": 5
    },
    {
      "tile": {
        "sheet": 38,
        "col": 0,
        "row": 8
      },
      "x": 70,
      "y": 45
    },
    {
      "tile": {
        "sheet": 38,
        "col": 0,
        "row": 8
      },
      "x": 29,
      "y": 14
    },
    {
      "tile": {
        "sheet": 38,
        "col": 4,
        "row": 4
      },
      "x": 94,
      "y": 5
    },
    {
      "tile": {
        "sheet": 38,
        "col": 5,
        "row": 9
      },
      "x": 4,
      "y": 6
    },
    {
      "tile": {
        "sheet": 38,
        "col": 0,
        "row": 8
      },
      "x": 75,
      "y": 17
    },
    {
      "tile": {
        "sheet": 38,
        "col": 4,
        "row": 4
      },
      "x": 95,
      "y": 5
    },
    {
      "tile": {
        "sheet": 38,
        "col": 5,
        "row": 9
      },
      "x": 109,
      "y": 7
    },
    {
      "tile": {
        "sheet": 38,
        "col": 2,
        "row": 9
      },
      "x": 5,
      "y": 8
    },
    {
      "tile": {
        "sheet": 38,
        "col": 0,
        "row": 8
      },
      "x": 91,
      "y": 6
    },
    {
      "tile": {
        "sheet": 38,
        "col": 0,
        "row": 8
      },
      "x": 24,
      "y": 14
    },
    {
      "tile": {
        "sheet": 38,
        "col": 0,
        "row": 8
      },
      "x": 43,
      "y": 53
    },
    {
      "tile": {
        "sheet": 38,
        "col": 0,
        "row": 8
      },
      "x": 96,
      "y": 6
    },
    {
      "tile": {
        "sheet": 38,
        "col": 1,
        "row": 11
      },
      "x": 5,
      "y": 19
    },
    {
      "tile": {
        "sheet": 38,
        "col": 2,
        "row": 8
      },
      "x": 28,
      "y": 18
    },
    {
      "tile": {
        "sheet": 38,
        "col": 5,
        "row": 9
      },
      "x": 108,
      "y": 2
    },
    {
      "tile": {
        "sheet": 38,
        "col": 4,
        "row": 4
      },
      "x": 21,
      "y": 58
    },
    {
      "tile": {
        "sheet": 38,
        "col": 5,
        "row": 9
      },
      "x": 109,
      "y": 2
    },
    {
      "tile": {
        "sheet": 38,
        "col": 5,
        "row": 9
      },
      "x": 93,
      "y": 60
    },
    {
      "tile": {
        "sheet": 38,
        "col": 5,
        "row": 9
      },
      "x": 40,
      "y": 17
    },
    {
      "tile": {
        "sheet": 38,
        "col": 5,
        "row": 9
      },
      "x": 110,
      "y": 7
    },
    {
      "tile": {
        "sheet": 38,
        "col": 0,
        "row": 8
      },
      "x": 64,
      "y": 20
    },
    {
      "tile": {
        "sheet": 38,
        "col": 4,
        "row": 4
      },
      "x": 37,
      "y": 57
    },
    {
      "tile": {
        "sheet": 38,
        "col": 0,
        "row": 8
      },
      "x": 43,
      "y": 7
    },
    {
      "tile": {
        "sheet": 38,
        "col": 0,
        "row": 8
      },
      "x": 38,
      "y": 2
    },
    {
      "tile": {
        "sheet": 38,
        "col": 5,
        "row": 9
      },
      "x": 2,
      "y": 3
    },
    {
      "tile": {
        "sheet": 38,
        "col": 0,
        "row": 3
      },
      "x": 2,
      "y": 67
    },
    {
      "tile": {
        "sheet": 38,
        "col": 0,
        "row": 8
      },
      "x": 38,
      "y": 7
    },
    {
      "tile": {
        "sheet": 38,
        "col": 5,
        "row": 9
      },
      "x": 78,
      "y": 31
    },
    {
      "tile": {
        "sheet": 38,
        "col": 0,
        "row": 8
      },
      "x": 43,
      "y": 2
    },
    {
      "tile": {
        "sheet": 38,
        "col": 4,
        "row": 4
      },
      "x": 29,
      "y": 46
    },
    {
      "tile": {
        "sheet": 38,
        "col": 0,
        "row": 8
      },
      "x": 24,
      "y": 19
    },
    {
      "tile": {
        "sheet": 38,
        "col": 2,
        "row": 8
      },
      "x": 39,
      "y": 4
    },
    {
      "tile": {
        "sheet": 38,
        "col": 2,
        "row": 8
      },
      "x": 39,
      "y": 6
    },
    {
      "tile": {
        "sheet": 38,
        "col": 2,
        "row": 8
      },
      "x": 42,
      "y": 6
    },
    {
      "tile": {
        "sheet": 38,
        "col": 4,
        "row": 4
      },
      "x": 24,
      "y": 58
    },
    {
      "tile": {
        "sheet": 38,
        "col": 5,
        "row": 9
      },
      "x": 55,
      "y": 29
    },
    {
      "tile": {
        "sheet": 38,
        "col": 3,
        "row": 8
      },
      "x": 79,
      "y": 5
    },
    {
      "tile": {
        "sheet": 38,
        "col": 5,
        "row": 9
      },
      "x": 1,
      "y": 3
    },
    {
      "tile": {
        "sheet": 38,
        "col": 0,
        "row": 3
      },
      "x": 96,
      "y": 43
    },
    {
      "tile": {
        "sheet": 38,
        "col": 1,
        "row": 11
      },
      "x": 8,
      "y": 19
    },
    {
      "tile": {
        "sheet": 38,
        "col": 5,
        "row": 9
      },
      "x": 5,
      "y": 6
    },
    {
      "tile": {
        "sheet": 38,
        "col": 3,
        "row": 3
      },
      "x": 62,
      "y": 18
    },
    {
      "tile": {
        "sheet": 38,
        "col": 0,
        "row": 8
      },
      "x": 59,
      "y": 15
    },
    {
      "tile": {
        "sheet": 38,
        "col": 2,
        "row": 9
      },
      "x": 4,
      "y": 8
    },
    {
      "tile": {
        "sheet": 38,
        "col": 2,
        "row": 8
      },
      "x": 25,
      "y": 18
    },
    {
      "tile": {
        "sheet": 38,
        "col": 0,
        "row": 8
      },
      "x": 29,
      "y": 19
    },
    {
      "tile": {
        "sheet": 38,
        "col": 0,
        "row": 8
      },
      "x": 64,
      "y": 15
    },
    {
      "tile": {
        "sheet": 38,
        "col": 4,
        "row": 4
      },
      "x": 22,
      "y": 58
    },
    {
      "tile": {
        "sheet": 38,
        "col": 0,
        "row": 3
      },
      "x": 60,
      "y": 16
    },
    {
      "tile": {
        "sheet": 38,
        "col": 4,
        "row": 4
      },
      "x": 23,
      "y": 58
    },
    {
      "tile": {
        "sheet": 38,
        "col": 3,
        "row": 3
      },
      "x": 63,
      "y": 18
    },
    {
      "tile": {
        "sheet": 38,
        "col": 1,
        "row": 11
      },
      "x": 4,
      "y": 19
    },
    {
      "tile": {
        "sheet": 38,
        "col": 0,
        "row": 8
      },
      "x": 59,
      "y": 20
    },
    {
      "tile": {
        "sheet": 38,
        "col": 0,
        "row": 8
      },
      "x": 110,
      "y": 14
    },
    {
      "tile": {
        "sheet": 38,
        "col": 0,
        "row": 8
      },
      "x": 110,
      "y": 19
    },
    {
      "tile": {
        "sheet": 38,
        "col": 4,
        "row": 4
      },
      "x": 41,
      "y": 57
    },
    {
      "tile": {
        "sheet": 38,
        "col": 0,
        "row": 8
      },
      "x": 115,
      "y": 19
    },
    {
      "tile": {
        "sheet": 38,
        "col": 0,
        "row": 8
      },
      "x": 3,
      "y": 16
    },
    {
      "tile": {
        "sheet": 38,
        "col": 0,
        "row": 8
      },
      "x": 10,
      "y": 16
    },
    {
      "tile": {
        "sheet": 38,
        "col": 4,
        "row": 4
      },
      "x": 30,
      "y": 43
    },
    {
      "tile": {
        "sheet": 38,
        "col": 0,
        "row": 11
      },
      "x": 4,
      "y": 17
    },
    {
      "tile": {
        "sheet": 38,
        "col": 0,
        "row": 11
      },
      "x": 9,
      "y": 17
    },
    {
      "tile": {
        "sheet": 38,
        "col": 1,
        "row": 11
      },
      "x": 9,
      "y": 19
    },
    {
      "tile": {
        "sheet": 38,
        "col": 0,
        "row": 8
      },
      "x": 3,
      "y": 21
    },
    {
      "tile": {
        "sheet": 38,
        "col": 0,
        "row": 8
      },
      "x": 10,
      "y": 21
    },
    {
      "tile": {
        "sheet": 38,
        "col": 4,
        "row": 4
      },
      "x": 92,
      "y": 34
    },
    {
      "tile": {
        "sheet": 38,
        "col": 5,
        "row": 9
      },
      "x": 39,
      "y": 17
    },
    {
      "tile": {
        "sheet": 38,
        "col": 5,
        "row": 9
      },
      "x": 44,
      "y": 20
    },
    {
      "tile": {
        "sheet": 38,
        "col": 5,
        "row": 9
      },
      "x": 40,
      "y": 22
    },
    {
      "tile": {
        "sheet": 38,
        "col": 1,
        "row": 11
      },
      "x": 111,
      "y": 32
    },
    {
      "tile": {
        "sheet": 38,
        "col": 5,
        "row": 9
      },
      "x": 41,
      "y": 22
    },
    {
      "tile": {
        "sheet": 38,
        "col": 0,
        "row": 8
      },
      "x": 80,
      "y": 17
    },
    {
      "tile": {
        "sheet": 38,
        "col": 0,
        "row": 8
      },
      "x": 109,
      "y": 75
    },
    {
      "tile": {
        "sheet": 38,
        "col": 4,
        "row": 4
      },
      "x": 41,
      "y": 47
    },
    {
      "tile": {
        "sheet": 38,
        "col": 4,
        "row": 4
      },
      "x": 89,
      "y": 31
    },
    {
      "tile": {
        "sheet": 38,
        "col": 0,
        "row": 3
      },
      "x": 76,
      "y": 18
    },
    {
      "tile": {
        "sheet": 38,
        "col": 0,
        "row": 3
      },
      "x": 77,
      "y": 18
    },
    {
      "tile": {
        "sheet": 38,
        "col": 3,
        "row": 3
      },
      "x": 78,
      "y": 20
    },
    {
      "tile": {
        "sheet": 38,
        "col": 4,
        "row": 4
      },
      "x": 20,
      "y": 55
    },
    {
      "tile": {
        "sheet": 38,
        "col": 5,
        "row": 9
      },
      "x": 59,
      "y": 32
    },
    {
      "tile": {
        "sheet": 38,
        "col": 3,
        "row": 3
      },
      "x": 79,
      "y": 20
    },
    {
      "tile": {
        "sheet": 38,
        "col": 0,
        "row": 8
      },
      "x": 80,
      "y": 22
    },
    {
      "tile": {
        "sheet": 38,
        "col": 3,
        "row": 3
      },
      "x": 98,
      "y": 45
    },
    {
      "tile": {
        "sheet": 38,
        "col": 5,
        "row": 9
      },
      "x": 92,
      "y": 19
    },
    {
      "tile": {
        "sheet": 38,
        "col": 5,
        "row": 9
      },
      "x": 93,
      "y": 19
    },
    {
      "tile": {
        "sheet": 38,
        "col": 4,
        "row": 4
      },
      "x": 24,
      "y": 55
    },
    {
      "tile": {
        "sheet": 38,
        "col": 5,
        "row": 9
      },
      "x": 97,
      "y": 22
    },
    {
      "tile": {
        "sheet": 38,
        "col": 5,
        "row": 9
      },
      "x": 93,
      "y": 24
    },
    {
      "tile": {
        "sheet": 38,
        "col": 5,
        "row": 9
      },
      "x": 94,
      "y": 24
    },
    {
      "tile": {
        "sheet": 38,
        "col": 5,
        "row": 9
      },
      "x": 22,
      "y": 28
    },
    {
      "tile": {
        "sheet": 38,
        "col": 5,
        "row": 9
      },
      "x": 23,
      "y": 28
    },
    {
      "tile": {
        "sheet": 38,
        "col": 0,
        "row": 3
      },
      "x": 41,
      "y": 29
    },
    {
      "tile": {
        "sheet": 38,
        "col": 5,
        "row": 9
      },
      "x": 27,
      "y": 31
    },
    {
      "tile": {
        "sheet": 38,
        "col": 5,
        "row": 9
      },
      "x": 23,
      "y": 33
    },
    {
      "tile": {
        "sheet": 38,
        "col": 5,
        "row": 9
      },
      "x": 24,
      "y": 33
    },
    {
      "tile": {
        "sheet": 38,
        "col": 0,
        "row": 8
      },
      "x": 40,
      "y": 28
    },
    {
      "tile": {
        "sheet": 38,
        "col": 0,
        "row": 8
      },
      "x": 1,
      "y": 66
    },
    {
      "tile": {
        "sheet": 38,
        "col": 0,
        "row": 8
      },
      "x": 47,
      "y": 28
    },
    {
      "tile": {
        "sheet": 38,
        "col": 0,
        "row": 3
      },
      "x": 42,
      "y": 29
    },
    {
      "tile": {
        "sheet": 38,
        "col": 3,
        "row": 3
      },
      "x": 45,
      "y": 29
    },
    {
      "tile": {
        "sheet": 38,
        "col": 3,
        "row": 3
      },
      "x": 46,
      "y": 29
    },
    {
      "tile": {
        "sheet": 38,
        "col": 5,
        "row": 3
      },
      "x": 41,
      "y": 32
    },
    {
      "tile": {
        "sheet": 38,
        "col": 5,
        "row": 3
      },
      "x": 42,
      "y": 32
    },
    {
      "tile": {
        "sheet": 38,
        "col": 1,
        "row": 3
      },
      "x": 45,
      "y": 32
    },
    {
      "tile": {
        "sheet": 38,
        "col": 4,
        "row": 4
      },
      "x": 20,
      "y": 58
    },
    {
      "tile": {
        "sheet": 38,
        "col": 1,
        "row": 3
      },
      "x": 46,
      "y": 32
    },
    {
      "tile": {
        "sheet": 38,
        "col": 0,
        "row": 8
      },
      "x": 40,
      "y": 33
    },
    {
      "tile": {
        "sheet": 38,
        "col": 0,
        "row": 8
      },
      "x": 47,
      "y": 33
    },
    {
      "tile": {
        "sheet": 38,
        "col": 5,
        "row": 9
      },
      "x": 40,
      "y": 69
    },
    {
      "tile": {
        "sheet": 38,
        "col": 0,
        "row": 8
      },
      "x": 7,
      "y": 34
    },
    {
      "tile": {
        "sheet": 38,
        "col": 5,
        "row": 9
      },
      "x": 73,
      "y": 28
    },
    {
      "tile": {
        "sheet": 38,
        "col": 5,
        "row": 9
      },
      "x": 74,
      "y": 28
    },
    {
      "tile": {
        "sheet": 38,
        "col": 5,
        "row": 9
      },
      "x": 74,
      "y": 33
    },
    {
      "tile": {
        "sheet": 38,
        "col": 5,
        "row": 9
      },
      "x": 75,
      "y": 33
    },
    {
      "tile": {
        "sheet": 38,
        "col": 0,
        "row": 8
      },
      "x": 7,
      "y": 29
    },
    {
      "tile": {
        "sheet": 38,
        "col": 0,
        "row": 3
      },
      "x": 91,
      "y": 5
    },
    {
      "tile": {
        "sheet": 38,
        "col": 4,
        "row": 4
      },
      "x": 8,
      "y": 30
    },
    {
      "tile": {
        "sheet": 38,
        "col": 4,
        "row": 4
      },
      "x": 9,
      "y": 30
    },
    {
      "tile": {
        "sheet": 38,
        "col": 0,
        "row": 8
      },
      "x": 94,
      "y": 42
    },
    {
      "tile": {
        "sheet": 38,
        "col": 4,
        "row": 4
      },
      "x": 10,
      "y": 30
    },
    {
      "tile": {
        "sheet": 38,
        "col": 4,
        "row": 4
      },
      "x": 11,
      "y": 30
    },
    {
      "tile": {
        "sheet": 38,
        "col": 4,
        "row": 4
      },
      "x": 8,
      "y": 33
    },
    {
      "tile": {
        "sheet": 38,
        "col": 5,
        "row": 9
      },
      "x": 42,
      "y": 74
    },
    {
      "tile": {
        "sheet": 38,
        "col": 4,
        "row": 4
      },
      "x": 9,
      "y": 33
    },
    {
      "tile": {
        "sheet": 38,
        "col": 4,
        "row": 4
      },
      "x": 10,
      "y": 33
    },
    {
      "tile": {
        "sheet": 38,
        "col": 4,
        "row": 4
      },
      "x": 11,
      "y": 33
    },
    {
      "tile": {
        "sheet": 38,
        "col": 2,
        "row": 9
      },
      "x": 109,
      "y": 59
    },
    {
      "tile": {
        "sheet": 38,
        "col": 0,
        "row": 8
      },
      "x": 75,
      "y": 45
    },
    {
      "tile": {
        "sheet": 38,
        "col": 0,
        "row": 8
      },
      "x": 12,
      "y": 34
    },
    {
      "tile": {
        "sheet": 38,
        "col": 5,
        "row": 9
      },
      "x": 54,
      "y": 29
    },
    {
      "tile": {
        "sheet": 38,
        "col": 5,
        "row": 9
      },
      "x": 55,
      "y": 34
    },
    {
      "tile": {
        "sheet": 38,
        "col": 4,
        "row": 4
      },
      "x": 21,
      "y": 55
    },
    {
      "tile": {
        "sheet": 38,
        "col": 5,
        "row": 9
      },
      "x": 56,
      "y": 34
    },
    {
      "tile": {
        "sheet": 38,
        "col": 0,
        "row": 8
      },
      "x": 106,
      "y": 29
    },
    {
      "tile": {
        "sheet": 38,
        "col": 0,
        "row": 8
      },
      "x": 113,
      "y": 29
    },
    {
      "tile": {
        "sheet": 38,
        "col": 0,
        "row": 8
      },
      "x": 63,
      "y": 74
    },
    {
      "tile": {
        "sheet": 38,
        "col": 0,
        "row": 11
      },
      "x": 107,
      "y": 30
    },
    {
      "tile": {
        "sheet": 38,
        "col": 0,
        "row": 11
      },
      "x": 108,
      "y": 30
    },
    {
      "tile": {
        "sheet": 38,
        "col": 0,
        "row": 11
      },
      "x": 111,
      "y": 30
    },
    {
      "tile": {
        "sheet": 38,
        "col": 0,
        "row": 11
      },
      "x": 112,
      "y": 30
    },
    {
      "tile": {
        "sheet": 38,
        "col": 4,
        "row": 4
      },
      "x": 44,
      "y": 47
    },
    {
      "tile": {
        "sheet": 38,
        "col": 1,
        "row": 11
      },
      "x": 107,
      "y": 32
    },
    {
      "tile": {
        "sheet": 38,
        "col": 4,
        "row": 4
      },
      "x": 19,
      "y": 55
    },
    {
      "tile": {
        "sheet": 38,
        "col": 1,
        "row": 11
      },
      "x": 108,
      "y": 32
    },
    {
      "tile": {
        "sheet": 38,
        "col": 1,
        "row": 11
      },
      "x": 112,
      "y": 32
    },
    {
      "tile": {
        "sheet": 38,
        "col": 0,
        "row": 8
      },
      "x": 106,
      "y": 34
    },
    {
      "tile": {
        "sheet": 38,
        "col": 0,
        "row": 8
      },
      "x": 113,
      "y": 34
    },
    {
      "tile": {
        "sheet": 38,
        "col": 0,
        "row": 8
      },
      "x": 87,
      "y": 30
    },
    {
      "tile": {
        "sheet": 38,
        "col": 0,
        "row": 8
      },
      "x": 94,
      "y": 30
    },
    {
      "tile": {
        "sheet": 38,
        "col": 4,
        "row": 4
      },
      "x": 93,
      "y": 34
    },
    {
      "tile": {
        "sheet": 38,
        "col": 4,
        "row": 4
      },
      "x": 88,
      "y": 31
    },
    {
      "tile": {
        "sheet": 38,
        "col": 4,
        "row": 4
      },
      "x": 42,
      "y": 47
    },
    {
      "tile": {
        "sheet": 38,
        "col": 4,
        "row": 4
      },
      "x": 90,
      "y": 31
    },
    {
      "tile": {
        "sheet": 38,
        "col": 4,
        "row": 4
      },
      "x": 92,
      "y": 31
    },
    {
      "tile": {
        "sheet": 38,
        "col": 0,
        "row": 11
      },
      "x": 9,
      "y": 43
    },
    {
      "tile": {
        "sheet": 38,
        "col": 4,
        "row": 4
      },
      "x": 88,
      "y": 34
    },
    {
      "tile": {
        "sheet": 38,
        "col": 4,
        "row": 4
      },
      "x": 93,
      "y": 31
    },
    {
      "tile": {
        "sheet": 38,
        "col": 4,
        "row": 4
      },
      "x": 89,
      "y": 34
    },
    {
      "tile": {
        "sheet": 38,
        "col": 4,
        "row": 4
      },
      "x": 90,
      "y": 34
    },
    {
      "tile": {
        "sheet": 38,
        "col": 0,
        "row": 8
      },
      "x": 87,
      "y": 35
    },
    {
      "tile": {
        "sheet": 38,
        "col": 0,
        "row": 8
      },
      "x": 94,
      "y": 35
    },
    {
      "tile": {
        "sheet": 38,
        "col": 0,
        "row": 8
      },
      "x": 70,
      "y": 40
    },
    {
      "tile": {
        "sheet": 38,
        "col": 0,
        "row": 8
      },
      "x": 75,
      "y": 40
    },
    {
      "tile": {
        "sheet": 38,
        "col": 0,
        "row": 8
      },
      "x": 108,
      "y": 41
    },
    {
      "tile": {
        "sheet": 38,
        "col": 0,
        "row": 8
      },
      "x": 115,
      "y": 41
    },
    {
      "tile": {
        "sheet": 38,
        "col": 0,
        "row": 11
      },
      "x": 109,
      "y": 42
    },
    {
      "tile": {
        "sheet": 38,
        "col": 0,
        "row": 11
      },
      "x": 110,
      "y": 42
    },
    {
      "tile": {
        "sheet": 38,
        "col": 4,
        "row": 4
      },
      "x": 42,
      "y": 57
    },
    {
      "tile": {
        "sheet": 38,
        "col": 0,
        "row": 11
      },
      "x": 113,
      "y": 42
    },
    {
      "tile": {
        "sheet": 38,
        "col": 0,
        "row": 11
      },
      "x": 114,
      "y": 42
    },
    {
      "tile": {
        "sheet": 38,
        "col": 1,
        "row": 11
      },
      "x": 109,
      "y": 44
    },
    {
      "tile": {
        "sheet": 38,
        "col": 1,
        "row": 11
      },
      "x": 110,
      "y": 44
    },
    {
      "tile": {
        "sheet": 38,
        "col": 1,
        "row": 11
      },
      "x": 113,
      "y": 44
    },
    {
      "tile": {
        "sheet": 38,
        "col": 1,
        "row": 11
      },
      "x": 114,
      "y": 44
    },
    {
      "tile": {
        "sheet": 38,
        "col": 0,
        "row": 8
      },
      "x": 108,
      "y": 46
    },
    {
      "tile": {
        "sheet": 38,
        "col": 0,
        "row": 8
      },
      "x": 115,
      "y": 46
    },
    {
      "tile": {
        "sheet": 38,
        "col": 0,
        "row": 8
      },
      "x": 54,
      "y": 41
    },
    {
      "tile": {
        "sheet": 38,
        "col": 0,
        "row": 8
      },
      "x": 59,
      "y": 41
    },
    {
      "tile": {
        "sheet": 38,
        "col": 3,
        "row": 3
      },
      "x": 97,
      "y": 45
    },
    {
      "tile": {
        "sheet": 38,
        "col": 2,
        "row": 8
      },
      "x": 55,
      "y": 43
    },
    {
      "tile": {
        "sheet": 38,
        "col": 2,
        "row": 8
      },
      "x": 58,
      "y": 43
    },
    {
      "tile": {
        "sheet": 38,
        "col": 2,
        "row": 8
      },
      "x": 55,
      "y": 45
    },
    {
      "tile": {
        "sheet": 38,
        "col": 4,
        "row": 4
      },
      "x": 41,
      "y": 54
    },
    {
      "tile": {
        "sheet": 38,
        "col": 2,
        "row": 8
      },
      "x": 58,
      "y": 45
    },
    {
      "tile": {
        "sheet": 38,
        "col": 0,
        "row": 8
      },
      "x": 54,
      "y": 46
    },
    {
      "tile": {
        "sheet": 38,
        "col": 0,
        "row": 8
      },
      "x": 59,
      "y": 46
    },
    {
      "tile": {
        "sheet": 38,
        "col": 0,
        "row": 8
      },
      "x": 8,
      "y": 42
    },
    {
      "tile": {
        "sheet": 38,
        "col": 0,
        "row": 11
      },
      "x": 72,
      "y": 55
    },
    {
      "tile": {
        "sheet": 38,
        "col": 0,
        "row": 8
      },
      "x": 13,
      "y": 42
    },
    {
      "tile": {
        "sheet": 38,
        "col": 0,
        "row": 11
      },
      "x": 10,
      "y": 43
    },
    {
      "tile": {
        "sheet": 38,
        "col": 1,
        "row": 11
      },
      "x": 11,
      "y": 45
    },
    {
      "tile": {
        "sheet": 38,
        "col": 1,
        "row": 11
      },
      "x": 12,
      "y": 45
    },
    {
      "tile": {
        "sheet": 38,
        "col": 0,
        "row": 8
      },
      "x": 8,
      "y": 47
    },
    {
      "tile": {
        "sheet": 38,
        "col": 0,
        "row": 8
      },
      "x": 13,
      "y": 47
    },
    {
      "tile": {
        "sheet": 38,
        "col": 0,
        "row": 8
      },
      "x": 31,
      "y": 42
    },
    {
      "tile": {
        "sheet": 38,
        "col": 4,
        "row": 4
      },
      "x": 27,
      "y": 43
    },
    {
      "tile": {
        "sheet": 38,
        "col": 4,
        "row": 4
      },
      "x": 28,
      "y": 43
    },
    {
      "tile": {
        "sheet": 38,
        "col": 4,
        "row": 4
      },
      "x": 29,
      "y": 43
    },
    {
      "tile": {
        "sheet": 38,
        "col": 4,
        "row": 4
      },
      "x": 41,
      "y": 44
    },
    {
      "tile": {
        "sheet": 38,
        "col": 4,
        "row": 4
      },
      "x": 27,
      "y": 46
    },
    {
      "tile": {
        "sheet": 38,
        "col": 0,
        "row": 3
      },
      "x": 96,
      "y": 2
    },
    {
      "tile": {
        "sheet": 38,
        "col": 4,
        "row": 4
      },
      "x": 28,
      "y": 46
    },
    {
      "tile": {
        "sheet": 38,
        "col": 4,
        "row": 4
      },
      "x": 44,
      "y": 44
    },
    {
      "tile": {
        "sheet": 38,
        "col": 4,
        "row": 4
      },
      "x": 30,
      "y": 46
    },
    {
      "tile": {
        "sheet": 38,
        "col": 2,
        "row": 9
      },
      "x": 110,
      "y": 59
    },
    {
      "tile": {
        "sheet": 38,
        "col": 0,
        "row": 8
      },
      "x": 26,
      "y": 47
    },
    {
      "tile": {
        "sheet": 38,
        "col": 3,
        "row": 3
      },
      "x": 5,
      "y": 69
    },
    {
      "tile": {
        "sheet": 38,
        "col": 0,
        "row": 8
      },
      "x": 31,
      "y": 47
    },
    {
      "tile": {
        "sheet": 38,
        "col": 4,
        "row": 4
      },
      "x": 22,
      "y": 55
    },
    {
      "tile": {
        "sheet": 38,
        "col": 0,
        "row": 8
      },
      "x": 36,
      "y": 53
    },
    {
      "tile": {
        "sheet": 38,
        "col": 0,
        "row": 8
      },
      "x": 99,
      "y": 42
    },
    {
      "tile": {
        "sheet": 38,
        "col": 0,
        "row": 3
      },
      "x": 95,
      "y": 43
    },
    {
      "tile": {
        "sheet": 38,
        "col": 4,
        "row": 4
      },
      "x": 19,
      "y": 58
    },
    {
      "tile": {
        "sheet": 38,
        "col": 0,
        "row": 8
      },
      "x": 94,
      "y": 47
    },
    {
      "tile": {
        "sheet": 38,
        "col": 0,
        "row": 8
      },
      "x": 99,
      "y": 47
    },
    {
      "tile": {
        "sheet": 38,
        "col": 0,
        "row": 8
      },
      "x": 40,
      "y": 43
    },
    {
      "tile": {
        "sheet": 38,
        "col": 4,
        "row": 4
      },
      "x": 42,
      "y": 44
    },
    {
      "tile": {
        "sheet": 38,
        "col": 4,
        "row": 4
      },
      "x": 43,
      "y": 44
    },
    {
      "tile": {
        "sheet": 38,
        "col": 4,
        "row": 4
      },
      "x": 43,
      "y": 47
    },
    {
      "tile": {
        "sheet": 38,
        "col": 0,
        "row": 8
      },
      "x": 40,
      "y": 48
    },
    {
      "tile": {
        "sheet": 38,
        "col": 0,
        "row": 8
      },
      "x": 45,
      "y": 48
    },
    {
      "tile": {
        "sheet": 38,
        "col": 4,
        "row": 4
      },
      "x": 37,
      "y": 54
    },
    {
      "tile": {
        "sheet": 38,
        "col": 4,
        "row": 4
      },
      "x": 38,
      "y": 54
    },
    {
      "tile": {
        "sheet": 38,
        "col": 4,
        "row": 4
      },
      "x": 40,
      "y": 54
    },
    {
      "tile": {
        "sheet": 38,
        "col": 4,
        "row": 4
      },
      "x": 42,
      "y": 54
    },
    {
      "tile": {
        "sheet": 38,
        "col": 4,
        "row": 4
      },
      "x": 38,
      "y": 57
    },
    {
      "tile": {
        "sheet": 38,
        "col": 4,
        "row": 4
      },
      "x": 39,
      "y": 57
    },
    {
      "tile": {
        "sheet": 38,
        "col": 4,
        "row": 4
      },
      "x": 40,
      "y": 57
    },
    {
      "tile": {
        "sheet": 38,
        "col": 0,
        "row": 8
      },
      "x": 104,
      "y": 70
    },
    {
      "tile": {
        "sheet": 38,
        "col": 0,
        "row": 8
      },
      "x": 36,
      "y": 58
    },
    {
      "tile": {
        "sheet": 38,
        "col": 0,
        "row": 8
      },
      "x": 43,
      "y": 58
    },
    {
      "tile": {
        "sheet": 38,
        "col": 5,
        "row": 9
      },
      "x": 106,
      "y": 54
    },
    {
      "tile": {
        "sheet": 38,
        "col": 5,
        "row": 9
      },
      "x": 107,
      "y": 54
    },
    {
      "tile": {
        "sheet": 38,
        "col": 5,
        "row": 9
      },
      "x": 109,
      "y": 57
    },
    {
      "tile": {
        "sheet": 38,
        "col": 0,
        "row": 8
      },
      "x": 18,
      "y": 54
    },
    {
      "tile": {
        "sheet": 38,
        "col": 0,
        "row": 8
      },
      "x": 25,
      "y": 54
    },
    {
      "tile": {
        "sheet": 38,
        "col": 4,
        "row": 4
      },
      "x": 23,
      "y": 55
    },
    {
      "tile": {
        "sheet": 38,
        "col": 0,
        "row": 8
      },
      "x": 18,
      "y": 59
    },
    {
      "tile": {
        "sheet": 38,
        "col": 1,
        "row": 11
      },
      "x": 75,
      "y": 57
    },
    {
      "tile": {
        "sheet": 38,
        "col": 0,
        "row": 8
      },
      "x": 25,
      "y": 59
    },
    {
      "tile": {
        "sheet": 38,
        "col": 0,
        "row": 8
      },
      "x": 71,
      "y": 54
    },
    {
      "tile": {
        "sheet": 38,
        "col": 0,
        "row": 8
      },
      "x": 76,
      "y": 54
    },
    {
      "tile": {
        "sheet": 38,
        "col": 0,
        "row": 11
      },
      "x": 73,
      "y": 55
    },
    {
      "tile": {
        "sheet": 38,
        "col": 1,
        "row": 11
      },
      "x": 74,
      "y": 57
    },
    {
      "tile": {
        "sheet": 38,
        "col": 0,
        "row": 8
      },
      "x": 71,
      "y": 59
    },
    {
      "tile": {
        "sheet": 38,
        "col": 0,
        "row": 8
      },
      "x": 76,
      "y": 59
    },
    {
      "tile": {
        "sheet": 38,
        "col": 0,
        "row": 8
      },
      "x": 56,
      "y": 56
    },
    {
      "tile": {
        "sheet": 38,
        "col": 0,
        "row": 8
      },
      "x": 61,
      "y": 56
    },
    {
      "tile": {
        "sheet": 38,
        "col": 0,
        "row": 3
      },
      "x": 57,
      "y": 57
    },
    {
      "tile": {
        "sheet": 38,
        "col": 0,
        "row": 8
      },
      "x": 109,
      "y": 70
    },
    {
      "tile": {
        "sheet": 38,
        "col": 0,
        "row": 3
      },
      "x": 58,
      "y": 57
    },
    {
      "tile": {
        "sheet": 38,
        "col": 3,
        "row": 3
      },
      "x": 59,
      "y": 59
    },
    {
      "tile": {
        "sheet": 38,
        "col": 0,
        "row": 8
      },
      "x": 56,
      "y": 61
    },
    {
      "tile": {
        "sheet": 38,
        "col": 0,
        "row": 8
      },
      "x": 61,
      "y": 61
    },
    {
      "tile": {
        "sheet": 38,
        "col": 5,
        "row": 9
      },
      "x": 90,
      "y": 57
    },
    {
      "tile": {
        "sheet": 38,
        "col": 5,
        "row": 9
      },
      "x": 91,
      "y": 57
    },
    {
      "tile": {
        "sheet": 38,
        "col": 5,
        "row": 9
      },
      "x": 94,
      "y": 60
    },
    {
      "tile": {
        "sheet": 38,
        "col": 2,
        "row": 9
      },
      "x": 93,
      "y": 62
    },
    {
      "tile": {
        "sheet": 38,
        "col": 2,
        "row": 9
      },
      "x": 94,
      "y": 62
    },
    {
      "tile": {
        "sheet": 38,
        "col": 0,
        "row": 8
      },
      "x": 6,
      "y": 66
    },
    {
      "tile": {
        "sheet": 38,
        "col": 0,
        "row": 3
      },
      "x": 3,
      "y": 67
    },
    {
      "tile": {
        "sheet": 38,
        "col": 0,
        "row": 8
      },
      "x": 1,
      "y": 71
    },
    {
      "tile": {
        "sheet": 38,
        "col": 0,
        "row": 8
      },
      "x": 6,
      "y": 71
    },
    {
      "tile": {
        "sheet": 38,
        "col": 3,
        "row": 8
      },
      "x": 74,
      "y": 69
    },
    {
      "tile": {
        "sheet": 38,
        "col": 5,
        "row": 9
      },
      "x": 41,
      "y": 69
    },
    {
      "tile": {
        "sheet": 38,
        "col": 5,
        "row": 9
      },
      "x": 45,
      "y": 72
    },
    {
      "tile": {
        "sheet": 38,
        "col": 5,
        "row": 9
      },
      "x": 41,
      "y": 74
    },
    {
      "tile": {
        "sheet": 38,
        "col": 0,
        "row": 8
      },
      "x": 58,
      "y": 69
    },
    {
      "tile": {
        "sheet": 38,
        "col": 0,
        "row": 8
      },
      "x": 63,
      "y": 69
    },
    {
      "tile": {
        "sheet": 38,
        "col": 0,
        "row": 8
      },
      "x": 58,
      "y": 74
    },
    {
      "tile": {
        "sheet": 38,
        "col": 2,
        "row": 8
      },
      "x": 108,
      "y": 72
    },
    {
      "tile": {
        "sheet": 38,
        "col": 2,
        "row": 8
      },
      "x": 105,
      "y": 74
    },
    {
      "tile": {
        "sheet": 38,
        "col": 2,
        "row": 8
      },
      "x": 108,
      "y": 74
    },
    {
      "tile": {
        "sheet": 38,
        "col": 0,
        "row": 8
      },
      "x": 104,
      "y": 75
    },
    {
      "tile": {
        "sheet": 38,
        "col": 0,
        "row": 3
      },
      "x": 91,
      "y": 2
    },
    {
      "tile": {
        "sheet": 38,
        "col": 0,
        "row": 3
      },
      "x": 96,
      "y": 5
    }
  ],
  "1418819254_1": [
    {
      "tile": {
        "sheet": 38,
        "col": 1,
        "row": 11
      },
      "x": 89,
      "y": 8
    },
    {
      "tile": {
        "sheet": 38,
        "col": 0,
        "row": 8
      },
      "x": 40,
      "y": 1
    },
    {
      "tile": {
        "sheet": 38,
        "col": 0,
        "row": 8
      },
      "x": 110,
      "y": 74
    },
    {
      "tile": {
        "sheet": 38,
        "col": 0,
        "row": 8
      },
      "x": 45,
      "y": 1
    },
    {
      "tile": {
        "sheet": 38,
        "col": 2,
        "row": 8
      },
      "x": 41,
      "y": 2
    },
    {
      "tile": {
        "sheet": 38,
        "col": 4,
        "row": 4
      },
      "x": 44,
      "y": 20
    },
    {
      "tile": {
        "sheet": 38,
        "col": 2,
        "row": 8
      },
      "x": 42,
      "y": 2
    },
    {
      "tile": {
        "sheet": 38,
        "col": 4,
        "row": 4
      },
      "x": 108,
      "y": 18
    },
    {
      "tile": {
        "sheet": 38,
        "col": 4,
        "row": 4
      },
      "x": 73,
      "y": 47
    },
    {
      "tile": {
        "sheet": 38,
        "col": 4,
        "row": 4
      },
      "x": 7,
      "y": 17
    },
    {
      "tile": {
        "sheet": 38,
        "col": 6,
        "row": 10
      },
      "x": 42,
      "y": 4
    },
    {
      "tile": {
        "sheet": 38,
        "col": 0,
        "row": 8
      },
      "x": 45,
      "y": 59
    },
    {
      "tile": {
        "sheet": 38,
        "col": 4,
        "row": 4
      },
      "x": 42,
      "y": 20
    },
    {
      "tile": {
        "sheet": 38,
        "col": 1,
        "row": 11
      },
      "x": 55,
      "y": 17
    },
    {
      "tile": {
        "sheet": 38,
        "col": 0,
        "row": 8
      },
      "x": 92,
      "y": 18
    },
    {
      "tile": {
        "sheet": 38,
        "col": 2,
        "row": 8
      },
      "x": 44,
      "y": 2
    },
    {
      "tile": {
        "sheet": 38,
        "col": 7,
        "row": 10
      },
      "x": 43,
      "y": 4
    },
    {
      "tile": {
        "sheet": 38,
        "col": 0,
        "row": 8
      },
      "x": 60,
      "y": 75
    },
    {
      "tile": {
        "sheet": 38,
        "col": 2,
        "row": 8
      },
      "x": 45,
      "y": 2
    },
    {
      "tile": {
        "sheet": 38,
        "col": 0,
        "row": 8
      },
      "x": 40,
      "y": 6
    },
    {
      "tile": {
        "sheet": 38,
        "col": 0,
        "row": 8
      },
      "x": 45,
      "y": 6
    },
    {
      "tile": {
        "sheet": 38,
        "col": 0,
        "row": 8
      },
      "x": 11,
      "y": 16
    },
    {
      "tile": {
        "sheet": 38,
        "col": 0,
        "row": 11
      },
      "x": 60,
      "y": 15
    },
    {
      "tile": {
        "sheet": 38,
        "col": 0,
        "row": 8
      },
      "x": 24,
      "y": 3
    },
    {
      "tile": {
        "sheet": 38,
        "col": 0,
        "row": 8
      },
      "x": 29,
      "y": 3
    },
    {
      "tile": {
        "sheet": 38,
        "col": 1,
        "row": 11
      },
      "x": 88,
      "y": 8
    },
    {
      "tile": {
        "sheet": 38,
        "col": 0,
        "row": 8
      },
      "x": 110,
      "y": 14
    },
    {
      "tile": {
        "sheet": 38,
        "col": 0,
        "row": 8
      },
      "x": 24,
      "y": 8
    },
    {
      "tile": {
        "sheet": 38,
        "col": 1,
        "row": 11
      },
      "x": 93,
      "y": 8
    },
    {
      "tile": {
        "sheet": 38,
        "col": 0,
        "row": 8
      },
      "x": 29,
      "y": 8
    },
    {
      "tile": {
        "sheet": 38,
        "col": 4,
        "row": 4
      },
      "x": 109,
      "y": 15
    },
    {
      "tile": {
        "sheet": 38,
        "col": 0,
        "row": 8
      },
      "x": 87,
      "y": 5
    },
    {
      "tile": {
        "sheet": 38,
        "col": 4,
        "row": 4
      },
      "x": 42,
      "y": 17
    },
    {
      "tile": {
        "sheet": 38,
        "col": 0,
        "row": 8
      },
      "x": 94,
      "y": 5
    },
    {
      "tile": {
        "sheet": 38,
        "col": 0,
        "row": 8
      },
      "x": 22,
      "y": 40
    },
    {
      "tile": {
        "sheet": 38,
        "col": 1,
        "row": 11
      },
      "x": 26,
      "y": 20
    },
    {
      "tile": {
        "sheet": 38,
        "col": 0,
        "row": 11
      },
      "x": 88,
      "y": 6
    },
    {
      "tile": {
        "sheet": 38,
        "col": 4,
        "row": 4
      },
      "x": 109,
      "y": 18
    },
    {
      "tile": {
        "sheet": 38,
        "col": 2,
        "row": 12
      },
      "x": 75,
      "y": 68
    },
    {
      "tile": {
        "sheet": 38,
        "col": 0,
        "row": 11
      },
      "x": 89,
      "y": 6
    },
    {
      "tile": {
        "sheet": 38,
        "col": 0,
        "row": 3
      },
      "x": 72,
      "y": 18
    },
    {
      "tile": {
        "sheet": 38,
        "col": 0,
        "row": 11
      },
      "x": 92,
      "y": 6
    },
    {
      "tile": {
        "sheet": 38,
        "col": 4,
        "row": 4
      },
      "x": 108,
      "y": 15
    },
    {
      "tile": {
        "sheet": 38,
        "col": 0,
        "row": 11
      },
      "x": 93,
      "y": 6
    },
    {
      "tile": {
        "sheet": 38,
        "col": 0,
        "row": 8
      },
      "x": 105,
      "y": 69
    },
    {
      "tile": {
        "sheet": 38,
        "col": 1,
        "row": 11
      },
      "x": 92,
      "y": 8
    },
    {
      "tile": {
        "sheet": 38,
        "col": 1,
        "row": 11
      },
      "x": 44,
      "y": 57
    },
    {
      "tile": {
        "sheet": 38,
        "col": 0,
        "row": 8
      },
      "x": 87,
      "y": 10
    },
    {
      "tile": {
        "sheet": 38,
        "col": 0,
        "row": 8
      },
      "x": 94,
      "y": 10
    },
    {
      "tile": {
        "sheet": 38,
        "col": 0,
        "row": 11
      },
      "x": 26,
      "y": 18
    },
    {
      "tile": {
        "sheet": 38,
        "col": 0,
        "row": 8
      },
      "x": 40,
      "y": 16
    },
    {
      "tile": {
        "sheet": 38,
        "col": 0,
        "row": 8
      },
      "x": 54,
      "y": 14
    },
    {
      "tile": {
        "sheet": 38,
        "col": 0,
        "row": 8
      },
      "x": 61,
      "y": 14
    },
    {
      "tile": {
        "sheet": 38,
        "col": 0,
        "row": 11
      },
      "x": 55,
      "y": 15
    },
    {
      "tile": {
        "sheet": 38,
        "col": 4,
        "row": 4
      },
      "x": 43,
      "y": 20
    },
    {
      "tile": {
        "sheet": 38,
        "col": 0,
        "row": 11
      },
      "x": 56,
      "y": 15
    },
    {
      "tile": {
        "sheet": 38,
        "col": 0,
        "row": 11
      },
      "x": 59,
      "y": 15
    },
    {
      "tile": {
        "sheet": 38,
        "col": 1,
        "row": 11
      },
      "x": 56,
      "y": 17
    },
    {
      "tile": {
        "sheet": 38,
        "col": 1,
        "row": 11
      },
      "x": 59,
      "y": 17
    },
    {
      "tile": {
        "sheet": 38,
        "col": 2,
        "row": 12
      },
      "x": 22,
      "y": 59
    },
    {
      "tile": {
        "sheet": 38,
        "col": 1,
        "row": 11
      },
      "x": 60,
      "y": 17
    },
    {
      "tile": {
        "sheet": 38,
        "col": 0,
        "row": 8
      },
      "x": 110,
      "y": 19
    },
    {
      "tile": {
        "sheet": 38,
        "col": 0,
        "row": 8
      },
      "x": 45,
      "y": 16
    },
    {
      "tile": {
        "sheet": 38,
        "col": 0,
        "row": 8
      },
      "x": 54,
      "y": 19
    },
    {
      "tile": {
        "sheet": 38,
        "col": 0,
        "row": 8
      },
      "x": 6,
      "y": 16
    },
    {
      "tile": {
        "sheet": 38,
        "col": 0,
        "row": 8
      },
      "x": 61,
      "y": 19
    },
    {
      "tile": {
        "sheet": 38,
        "col": 0,
        "row": 8
      },
      "x": 105,
      "y": 14
    },
    {
      "tile": {
        "sheet": 38,
        "col": 4,
        "row": 4
      },
      "x": 106,
      "y": 15
    },
    {
      "tile": {
        "sheet": 38,
        "col": 4,
        "row": 4
      },
      "x": 107,
      "y": 15
    },
    {
      "tile": {
        "sheet": 38,
        "col": 4,
        "row": 4
      },
      "x": 106,
      "y": 18
    },
    {
      "tile": {
        "sheet": 38,
        "col": 4,
        "row": 4
      },
      "x": 107,
      "y": 18
    },
    {
      "tile": {
        "sheet": 38,
        "col": 0,
        "row": 8
      },
      "x": 105,
      "y": 19
    },
    {
      "tile": {
        "sheet": 38,
        "col": 4,
        "row": 4
      },
      "x": 76,
      "y": 44
    },
    {
      "tile": {
        "sheet": 38,
        "col": 4,
        "row": 4
      },
      "x": 41,
      "y": 17
    },
    {
      "tile": {
        "sheet": 38,
        "col": 4,
        "row": 4
      },
      "x": 43,
      "y": 17
    },
    {
      "tile": {
        "sheet": 38,
        "col": 5,
        "row": 3
      },
      "x": 72,
      "y": 21
    },
    {
      "tile": {
        "sheet": 38,
        "col": 4,
        "row": 4
      },
      "x": 44,
      "y": 17
    },
    {
      "tile": {
        "sheet": 38,
        "col": 4,
        "row": 4
      },
      "x": 41,
      "y": 20
    },
    {
      "tile": {
        "sheet": 38,
        "col": 0,
        "row": 8
      },
      "x": 40,
      "y": 21
    },
    {
      "tile": {
        "sheet": 38,
        "col": 2,
        "row": 12
      },
      "x": 26,
      "y": 74
    },
    {
      "tile": {
        "sheet": 38,
        "col": 0,
        "row": 8
      },
      "x": 45,
      "y": 21
    },
    {
      "tile": {
        "sheet": 38,
        "col": 4,
        "row": 4
      },
      "x": 8,
      "y": 17
    },
    {
      "tile": {
        "sheet": 38,
        "col": 2,
        "row": 12
      },
      "x": 22,
      "y": 54
    },
    {
      "tile": {
        "sheet": 38,
        "col": 4,
        "row": 4
      },
      "x": 9,
      "y": 17
    },
    {
      "tile": {
        "sheet": 38,
        "col": 4,
        "row": 4
      },
      "x": 10,
      "y": 17
    },
    {
      "tile": {
        "sheet": 38,
        "col": 4,
        "row": 4
      },
      "x": 7,
      "y": 20
    },
    {
      "tile": {
        "sheet": 38,
        "col": 4,
        "row": 4
      },
      "x": 8,
      "y": 20
    },
    {
      "tile": {
        "sheet": 38,
        "col": 4,
        "row": 4
      },
      "x": 9,
      "y": 20
    },
    {
      "tile": {
        "sheet": 38,
        "col": 4,
        "row": 4
      },
      "x": 10,
      "y": 20
    },
    {
      "tile": {
        "sheet": 38,
        "col": 0,
        "row": 8
      },
      "x": 6,
      "y": 21
    },
    {
      "tile": {
        "sheet": 38,
        "col": 0,
        "row": 8
      },
      "x": 11,
      "y": 21
    },
    {
      "tile": {
        "sheet": 38,
        "col": 0,
        "row": 8
      },
      "x": 71,
      "y": 17
    },
    {
      "tile": {
        "sheet": 38,
        "col": 0,
        "row": 8
      },
      "x": 78,
      "y": 17
    },
    {
      "tile": {
        "sheet": 38,
        "col": 0,
        "row": 3
      },
      "x": 73,
      "y": 18
    },
    {
      "tile": {
        "sheet": 38,
        "col": 4,
        "row": 4
      },
      "x": 41,
      "y": 47
    },
    {
      "tile": {
        "sheet": 38,
        "col": 0,
        "row": 8
      },
      "x": 27,
      "y": 45
    },
    {
      "tile": {
        "sheet": 38,
        "col": 3,
        "row": 3
      },
      "x": 76,
      "y": 18
    },
    {
      "tile": {
        "sheet": 38,
        "col": 3,
        "row": 3
      },
      "x": 77,
      "y": 18
    },
    {
      "tile": {
        "sheet": 38,
        "col": 5,
        "row": 3
      },
      "x": 73,
      "y": 21
    },
    {
      "tile": {
        "sheet": 38,
        "col": 1,
        "row": 3
      },
      "x": 77,
      "y": 21
    },
    {
      "tile": {
        "sheet": 38,
        "col": 2,
        "row": 12
      },
      "x": 27,
      "y": 74
    },
    {
      "tile": {
        "sheet": 38,
        "col": 0,
        "row": 8
      },
      "x": 71,
      "y": 22
    },
    {
      "tile": {
        "sheet": 38,
        "col": 0,
        "row": 8
      },
      "x": 78,
      "y": 22
    },
    {
      "tile": {
        "sheet": 38,
        "col": 0,
        "row": 8
      },
      "x": 21,
      "y": 17
    },
    {
      "tile": {
        "sheet": 38,
        "col": 0,
        "row": 8
      },
      "x": 37,
      "y": 48
    },
    {
      "tile": {
        "sheet": 38,
        "col": 0,
        "row": 8
      },
      "x": 28,
      "y": 17
    },
    {
      "tile": {
        "sheet": 38,
        "col": 4,
        "row": 4
      },
      "x": 40,
      "y": 44
    },
    {
      "tile": {
        "sheet": 38,
        "col": 0,
        "row": 11
      },
      "x": 22,
      "y": 18
    },
    {
      "tile": {
        "sheet": 38,
        "col": 0,
        "row": 11
      },
      "x": 23,
      "y": 18
    },
    {
      "tile": {
        "sheet": 38,
        "col": 0,
        "row": 11
      },
      "x": 27,
      "y": 18
    },
    {
      "tile": {
        "sheet": 38,
        "col": 1,
        "row": 11
      },
      "x": 22,
      "y": 20
    },
    {
      "tile": {
        "sheet": 38,
        "col": 1,
        "row": 11
      },
      "x": 23,
      "y": 20
    },
    {
      "tile": {
        "sheet": 38,
        "col": 2,
        "row": 12
      },
      "x": 80,
      "y": 71
    },
    {
      "tile": {
        "sheet": 38,
        "col": 1,
        "row": 11
      },
      "x": 27,
      "y": 20
    },
    {
      "tile": {
        "sheet": 38,
        "col": 0,
        "row": 8
      },
      "x": 21,
      "y": 22
    },
    {
      "tile": {
        "sheet": 38,
        "col": 0,
        "row": 8
      },
      "x": 28,
      "y": 22
    },
    {
      "tile": {
        "sheet": 38,
        "col": 0,
        "row": 8
      },
      "x": 87,
      "y": 18
    },
    {
      "tile": {
        "sheet": 38,
        "col": 0,
        "row": 3
      },
      "x": 88,
      "y": 19
    },
    {
      "tile": {
        "sheet": 38,
        "col": 0,
        "row": 3
      },
      "x": 89,
      "y": 19
    },
    {
      "tile": {
        "sheet": 38,
        "col": 3,
        "row": 3
      },
      "x": 90,
      "y": 21
    },
    {
      "tile": {
        "sheet": 38,
        "col": 0,
        "row": 11
      },
      "x": 57,
      "y": 71
    },
    {
      "tile": {
        "sheet": 38,
        "col": 3,
        "row": 3
      },
      "x": 91,
      "y": 21
    },
    {
      "tile": {
        "sheet": 38,
        "col": 0,
        "row": 8
      },
      "x": 87,
      "y": 23
    },
    {
      "tile": {
        "sheet": 38,
        "col": 0,
        "row": 8
      },
      "x": 92,
      "y": 23
    },
    {
      "tile": {
        "sheet": 38,
        "col": 0,
        "row": 8
      },
      "x": 39,
      "y": 29
    },
    {
      "tile": {
        "sheet": 38,
        "col": 0,
        "row": 8
      },
      "x": 46,
      "y": 29
    },
    {
      "tile": {
        "sheet": 38,
        "col": 0,
        "row": 11
      },
      "x": 40,
      "y": 30
    },
    {
      "tile": {
        "sheet": 38,
        "col": 0,
        "row": 11
      },
      "x": 44,
      "y": 30
    },
    {
      "tile": {
        "sheet": 38,
        "col": 0,
        "row": 11
      },
      "x": 45,
      "y": 30
    },
    {
      "tile": {
        "sheet": 38,
        "col": 2,
        "row": 12
      },
      "x": 26,
      "y": 34
    },
    {
      "tile": {
        "sheet": 38,
        "col": 1,
        "row": 11
      },
      "x": 40,
      "y": 32
    },
    {
      "tile": {
        "sheet": 38,
        "col": 1,
        "row": 11
      },
      "x": 41,
      "y": 32
    },
    {
      "tile": {
        "sheet": 38,
        "col": 1,
        "row": 11
      },
      "x": 44,
      "y": 32
    },
    {
      "tile": {
        "sheet": 38,
        "col": 1,
        "row": 11
      },
      "x": 45,
      "y": 32
    },
    {
      "tile": {
        "sheet": 38,
        "col": 0,
        "row": 8
      },
      "x": 39,
      "y": 34
    },
    {
      "tile": {
        "sheet": 38,
        "col": 2,
        "row": 12
      },
      "x": 77,
      "y": 73
    },
    {
      "tile": {
        "sheet": 38,
        "col": 0,
        "row": 8
      },
      "x": 46,
      "y": 34
    },
    {
      "tile": {
        "sheet": 38,
        "col": 0,
        "row": 8
      },
      "x": 106,
      "y": 30
    },
    {
      "tile": {
        "sheet": 38,
        "col": 0,
        "row": 8
      },
      "x": 62,
      "y": 57
    },
    {
      "tile": {
        "sheet": 38,
        "col": 0,
        "row": 8
      },
      "x": 113,
      "y": 30
    },
    {
      "tile": {
        "sheet": 38,
        "col": 0,
        "row": 11
      },
      "x": 107,
      "y": 31
    },
    {
      "tile": {
        "sheet": 38,
        "col": 0,
        "row": 11
      },
      "x": 108,
      "y": 31
    },
    {
      "tile": {
        "sheet": 38,
        "col": 0,
        "row": 11
      },
      "x": 111,
      "y": 31
    },
    {
      "tile": {
        "sheet": 38,
        "col": 2,
        "row": 12
      },
      "x": 24,
      "y": 71
    },
    {
      "tile": {
        "sheet": 38,
        "col": 0,
        "row": 11
      },
      "x": 112,
      "y": 31
    },
    {
      "tile": {
        "sheet": 38,
        "col": 1,
        "row": 11
      },
      "x": 107,
      "y": 33
    },
    {
      "tile": {
        "sheet": 38,
        "col": 1,
        "row": 11
      },
      "x": 108,
      "y": 33
    },
    {
      "tile": {
        "sheet": 38,
        "col": 1,
        "row": 11
      },
      "x": 111,
      "y": 33
    },
    {
      "tile": {
        "sheet": 38,
        "col": 1,
        "row": 11
      },
      "x": 112,
      "y": 33
    },
    {
      "tile": {
        "sheet": 38,
        "col": 0,
        "row": 8
      },
      "x": 106,
      "y": 35
    },
    {
      "tile": {
        "sheet": 38,
        "col": 0,
        "row": 8
      },
      "x": 42,
      "y": 48
    },
    {
      "tile": {
        "sheet": 38,
        "col": 0,
        "row": 8
      },
      "x": 113,
      "y": 35
    },
    {
      "tile": {
        "sheet": 38,
        "col": 2,
        "row": 12
      },
      "x": 22,
      "y": 31
    },
    {
      "tile": {
        "sheet": 38,
        "col": 2,
        "row": 12
      },
      "x": 23,
      "y": 31
    },
    {
      "tile": {
        "sheet": 38,
        "col": 2,
        "row": 12
      },
      "x": 25,
      "y": 34
    },
    {
      "tile": {
        "sheet": 38,
        "col": 2,
        "row": 9
      },
      "x": 25,
      "y": 36
    },
    {
      "tile": {
        "sheet": 38,
        "col": 2,
        "row": 9
      },
      "x": 26,
      "y": 36
    },
    {
      "tile": {
        "sheet": 38,
        "col": 0,
        "row": 8
      },
      "x": 27,
      "y": 40
    },
    {
      "tile": {
        "sheet": 38,
        "col": 0,
        "row": 8
      },
      "x": 22,
      "y": 45
    },
    {
      "tile": {
        "sheet": 38,
        "col": 2,
        "row": 12
      },
      "x": 55,
      "y": 41
    },
    {
      "tile": {
        "sheet": 38,
        "col": 2,
        "row": 12
      },
      "x": 56,
      "y": 41
    },
    {
      "tile": {
        "sheet": 38,
        "col": 0,
        "row": 11
      },
      "x": 41,
      "y": 55
    },
    {
      "tile": {
        "sheet": 38,
        "col": 2,
        "row": 12
      },
      "x": 58,
      "y": 44
    },
    {
      "tile": {
        "sheet": 38,
        "col": 2,
        "row": 12
      },
      "x": 59,
      "y": 44
    },
    {
      "tile": {
        "sheet": 38,
        "col": 2,
        "row": 9
      },
      "x": 58,
      "y": 46
    },
    {
      "tile": {
        "sheet": 38,
        "col": 2,
        "row": 9
      },
      "x": 59,
      "y": 46
    },
    {
      "tile": {
        "sheet": 38,
        "col": 0,
        "row": 8
      },
      "x": 37,
      "y": 43
    },
    {
      "tile": {
        "sheet": 38,
        "col": 0,
        "row": 8
      },
      "x": 42,
      "y": 43
    },
    {
      "tile": {
        "sheet": 38,
        "col": 4,
        "row": 4
      },
      "x": 39,
      "y": 44
    },
    {
      "tile": {
        "sheet": 38,
        "col": 4,
        "row": 4
      },
      "x": 41,
      "y": 44
    },
    {
      "tile": {
        "sheet": 38,
        "col": 4,
        "row": 4
      },
      "x": 38,
      "y": 47
    },
    {
      "tile": {
        "sheet": 38,
        "col": 4,
        "row": 4
      },
      "x": 39,
      "y": 47
    },
    {
      "tile": {
        "sheet": 38,
        "col": 4,
        "row": 4
      },
      "x": 40,
      "y": 47
    },
    {
      "tile": {
        "sheet": 38,
        "col": 0,
        "row": 8
      },
      "x": 105,
      "y": 42
    },
    {
      "tile": {
        "sheet": 38,
        "col": 0,
        "row": 8
      },
      "x": 110,
      "y": 42
    },
    {
      "tile": {
        "sheet": 38,
        "col": 0,
        "row": 8
      },
      "x": 105,
      "y": 47
    },
    {
      "tile": {
        "sheet": 38,
        "col": 0,
        "row": 8
      },
      "x": 110,
      "y": 47
    },
    {
      "tile": {
        "sheet": 38,
        "col": 3,
        "row": 8
      },
      "x": 4,
      "y": 45
    },
    {
      "tile": {
        "sheet": 38,
        "col": 0,
        "row": 8
      },
      "x": 72,
      "y": 43
    },
    {
      "tile": {
        "sheet": 38,
        "col": 0,
        "row": 8
      },
      "x": 79,
      "y": 43
    },
    {
      "tile": {
        "sheet": 38,
        "col": 4,
        "row": 4
      },
      "x": 73,
      "y": 44
    },
    {
      "tile": {
        "sheet": 38,
        "col": 4,
        "row": 4
      },
      "x": 74,
      "y": 44
    },
    {
      "tile": {
        "sheet": 38,
        "col": 4,
        "row": 4
      },
      "x": 75,
      "y": 44
    },
    {
      "tile": {
        "sheet": 38,
        "col": 4,
        "row": 4
      },
      "x": 77,
      "y": 44
    },
    {
      "tile": {
        "sheet": 38,
        "col": 4,
        "row": 4
      },
      "x": 78,
      "y": 44
    },
    {
      "tile": {
        "sheet": 38,
        "col": 4,
        "row": 4
      },
      "x": 74,
      "y": 47
    },
    {
      "tile": {
        "sheet": 38,
        "col": 4,
        "row": 4
      },
      "x": 75,
      "y": 47
    },
    {
      "tile": {
        "sheet": 38,
        "col": 4,
        "row": 4
      },
      "x": 76,
      "y": 47
    },
    {
      "tile": {
        "sheet": 38,
        "col": 1,
        "row": 11
      },
      "x": 59,
      "y": 73
    },
    {
      "tile": {
        "sheet": 38,
        "col": 4,
        "row": 4
      },
      "x": 77,
      "y": 47
    },
    {
      "tile": {
        "sheet": 38,
        "col": 4,
        "row": 4
      },
      "x": 78,
      "y": 47
    },
    {
      "tile": {
        "sheet": 38,
        "col": 2,
        "row": 12
      },
      "x": 23,
      "y": 71
    },
    {
      "tile": {
        "sheet": 38,
        "col": 0,
        "row": 8
      },
      "x": 57,
      "y": 57
    },
    {
      "tile": {
        "sheet": 38,
        "col": 0,
        "row": 8
      },
      "x": 72,
      "y": 48
    },
    {
      "tile": {
        "sheet": 38,
        "col": 0,
        "row": 8
      },
      "x": 79,
      "y": 48
    },
    {
      "tile": {
        "sheet": 38,
        "col": 0,
        "row": 8
      },
      "x": 40,
      "y": 54
    },
    {
      "tile": {
        "sheet": 38,
        "col": 0,
        "row": 8
      },
      "x": 45,
      "y": 54
    },
    {
      "tile": {
        "sheet": 38,
        "col": 0,
        "row": 11
      },
      "x": 42,
      "y": 55
    },
    {
      "tile": {
        "sheet": 38,
        "col": 1,
        "row": 11
      },
      "x": 43,
      "y": 57
    },
    {
      "tile": {
        "sheet": 38,
        "col": 2,
        "row": 12
      },
      "x": 26,
      "y": 57
    },
    {
      "tile": {
        "sheet": 38,
        "col": 0,
        "row": 8
      },
      "x": 40,
      "y": 59
    },
    {
      "tile": {
        "sheet": 38,
        "col": 2,
        "row": 12
      },
      "x": 21,
      "y": 54
    },
    {
      "tile": {
        "sheet": 38,
        "col": 2,
        "row": 12
      },
      "x": 23,
      "y": 59
    },
    {
      "tile": {
        "sheet": 38,
        "col": 0,
        "row": 8
      },
      "x": 70,
      "y": 55
    },
    {
      "tile": {
        "sheet": 38,
        "col": 0,
        "row": 8
      },
      "x": 75,
      "y": 55
    },
    {
      "tile": {
        "sheet": 38,
        "col": 4,
        "row": 4
      },
      "x": 71,
      "y": 56
    },
    {
      "tile": {
        "sheet": 38,
        "col": 4,
        "row": 4
      },
      "x": 72,
      "y": 56
    },
    {
      "tile": {
        "sheet": 38,
        "col": 4,
        "row": 4
      },
      "x": 73,
      "y": 56
    },
    {
      "tile": {
        "sheet": 38,
        "col": 4,
        "row": 4
      },
      "x": 74,
      "y": 56
    },
    {
      "tile": {
        "sheet": 38,
        "col": 4,
        "row": 4
      },
      "x": 71,
      "y": 59
    },
    {
      "tile": {
        "sheet": 38,
        "col": 4,
        "row": 4
      },
      "x": 72,
      "y": 59
    },
    {
      "tile": {
        "sheet": 38,
        "col": 4,
        "row": 4
      },
      "x": 73,
      "y": 59
    },
    {
      "tile": {
        "sheet": 38,
        "col": 4,
        "row": 4
      },
      "x": 74,
      "y": 59
    },
    {
      "tile": {
        "sheet": 38,
        "col": 0,
        "row": 8
      },
      "x": 70,
      "y": 60
    },
    {
      "tile": {
        "sheet": 38,
        "col": 2,
        "row": 9
      },
      "x": 27,
      "y": 76
    },
    {
      "tile": {
        "sheet": 38,
        "col": 0,
        "row": 8
      },
      "x": 75,
      "y": 60
    },
    {
      "tile": {
        "sheet": 38,
        "col": 0,
        "row": 8
      },
      "x": 57,
      "y": 62
    },
    {
      "tile": {
        "sheet": 38,
        "col": 0,
        "row": 8
      },
      "x": 62,
      "y": 62
    },
    {
      "tile": {
        "sheet": 38,
        "col": 2,
        "row": 12
      },
      "x": 76,
      "y": 68
    },
    {
      "tile": {
        "sheet": 38,
        "col": 2,
        "row": 12
      },
      "x": 76,
      "y": 73
    },
    {
      "tile": {
        "sheet": 38,
        "col": 0,
        "row": 8
      },
      "x": 110,
      "y": 69
    },
    {
      "tile": {
        "sheet": 38,
        "col": 0,
        "row": 8
      },
      "x": 105,
      "y": 74
    },
    {
      "tile": {
        "sheet": 38,
        "col": 0,
        "row": 8
      },
      "x": 55,
      "y": 70
    },
    {
      "tile": {
        "sheet": 38,
        "col": 0,
        "row": 8
      },
      "x": 60,
      "y": 70
    },
    {
      "tile": {
        "sheet": 38,
        "col": 0,
        "row": 11
      },
      "x": 56,
      "y": 71
    },
    {
      "tile": {
        "sheet": 38,
        "col": 0,
        "row": 8
      },
      "x": 55,
      "y": 75
    },
    {
      "tile": {
        "sheet": 38,
        "col": 2,
        "row": 9
      },
      "x": 26,
      "y": 76
    }
  ],
  "2103668303_1": [
    {
      "tile": {
        "sheet": 38,
        "col": 0,
        "row": 8
      },
      "x": 113,
      "y": 5
    },
    {
      "tile": {
        "sheet": 38,
        "col": 0,
        "row": 8
      },
      "x": 11,
      "y": 47
    },
    {
      "tile": {
        "sheet": 38,
        "col": 5,
        "row": 9
      },
      "x": 94,
      "y": 2
    },
    {
      "tile": {
        "sheet": 38,
        "col": 0,
        "row": 8
      },
      "x": 6,
      "y": 42
    },
    {
      "tile": {
        "sheet": 38,
        "col": 0,
        "row": 8
      },
      "x": 73,
      "y": 4
    },
    {
      "tile": {
        "sheet": 38,
        "col": 5,
        "row": 9
      },
      "x": 95,
      "y": 2
    },
    {
      "tile": {
        "sheet": 38,
        "col": 0,
        "row": 8
      },
      "x": 23,
      "y": 9
    },
    {
      "tile": {
        "sheet": 38,
        "col": 0,
        "row": 8
      },
      "x": 97,
      "y": 47
    },
    {
      "tile": {
        "sheet": 38,
        "col": 5,
        "row": 9
      },
      "x": 24,
      "y": 14
    },
    {
      "tile": {
        "sheet": 38,
        "col": 5,
        "row": 9
      },
      "x": 88,
      "y": 14
    },
    {
      "tile": {
        "sheet": 38,
        "col": 5,
        "row": 9
      },
      "x": 99,
      "y": 5
    },
    {
      "tile": {
        "sheet": 38,
        "col": 0,
        "row": 8
      },
      "x": 28,
      "y": 4
    },
    {
      "tile": {
        "sheet": 38,
        "col": 5,
        "row": 9
      },
      "x": 95,
      "y": 7
    },
    {
      "tile": {
        "sheet": 38,
        "col": 5,
        "row": 9
      },
      "x": 96,
      "y": 7
    },
    {
      "tile": {
        "sheet": 38,
        "col": 4,
        "row": 4
      },
      "x": 110,
      "y": 9
    },
    {
      "tile": {
        "sheet": 38,
        "col": 0,
        "row": 8
      },
      "x": 23,
      "y": 4
    },
    {
      "tile": {
        "sheet": 38,
        "col": 0,
        "row": 8
      },
      "x": 43,
      "y": 22
    },
    {
      "tile": {
        "sheet": 38,
        "col": 0,
        "row": 8
      },
      "x": 28,
      "y": 9
    },
    {
      "tile": {
        "sheet": 38,
        "col": 0,
        "row": 8
      },
      "x": 39,
      "y": 4
    },
    {
      "tile": {
        "sheet": 38,
        "col": 0,
        "row": 8
      },
      "x": 44,
      "y": 4
    },
    {
      "tile": {
        "sheet": 38,
        "col": 2,
        "row": 8
      },
      "x": 11,
      "y": 43
    },
    {
      "tile": {
        "sheet": 38,
        "col": 2,
        "row": 8
      },
      "x": 7,
      "y": 7
    },
    {
      "tile": {
        "sheet": 38,
        "col": 2,
        "row": 8
      },
      "x": 40,
      "y": 6
    },
    {
      "tile": {
        "sheet": 38,
        "col": 4,
        "row": 4
      },
      "x": 111,
      "y": 9
    },
    {
      "tile": {
        "sheet": 38,
        "col": 2,
        "row": 8
      },
      "x": 43,
      "y": 6
    },
    {
      "tile": {
        "sheet": 38,
        "col": 0,
        "row": 8
      },
      "x": 44,
      "y": 9
    },
    {
      "tile": {
        "sheet": 38,
        "col": 4,
        "row": 4
      },
      "x": 107,
      "y": 6
    },
    {
      "tile": {
        "sheet": 38,
        "col": 4,
        "row": 4
      },
      "x": 108,
      "y": 9
    },
    {
      "tile": {
        "sheet": 38,
        "col": 2,
        "row": 8
      },
      "x": 40,
      "y": 8
    },
    {
      "tile": {
        "sheet": 38,
        "col": 2,
        "row": 8
      },
      "x": 43,
      "y": 8
    },
    {
      "tile": {
        "sheet": 38,
        "col": 0,
        "row": 8
      },
      "x": 39,
      "y": 9
    },
    {
      "tile": {
        "sheet": 38,
        "col": 4,
        "row": 4
      },
      "x": 112,
      "y": 6
    },
    {
      "tile": {
        "sheet": 38,
        "col": 0,
        "row": 8
      },
      "x": 38,
      "y": 32
    },
    {
      "tile": {
        "sheet": 38,
        "col": 0,
        "row": 8
      },
      "x": 11,
      "y": 5
    },
    {
      "tile": {
        "sheet": 38,
        "col": 0,
        "row": 8
      },
      "x": 78,
      "y": 4
    },
    {
      "tile": {
        "sheet": 38,
        "col": 2,
        "row": 8
      },
      "x": 74,
      "y": 6
    },
    {
      "tile": {
        "sheet": 38,
        "col": 4,
        "row": 4
      },
      "x": 80,
      "y": 60
    },
    {
      "tile": {
        "sheet": 38,
        "col": 0,
        "row": 11
      },
      "x": 75,
      "y": 31
    },
    {
      "tile": {
        "sheet": 38,
        "col": 4,
        "row": 4
      },
      "x": 109,
      "y": 9
    },
    {
      "tile": {
        "sheet": 38,
        "col": 2,
        "row": 8
      },
      "x": 39,
      "y": 19
    },
    {
      "tile": {
        "sheet": 38,
        "col": 2,
        "row": 8
      },
      "x": 77,
      "y": 6
    },
    {
      "tile": {
        "sheet": 38,
        "col": 0,
        "row": 8
      },
      "x": 10,
      "y": 72
    },
    {
      "tile": {
        "sheet": 38,
        "col": 2,
        "row": 8
      },
      "x": 74,
      "y": 8
    },
    {
      "tile": {
        "sheet": 38,
        "col": 0,
        "row": 8
      },
      "x": 12,
      "y": 30
    },
    {
      "tile": {
        "sheet": 38,
        "col": 5,
        "row": 9
      },
      "x": 25,
      "y": 19
    },
    {
      "tile": {
        "sheet": 38,
        "col": 2,
        "row": 8
      },
      "x": 77,
      "y": 8
    },
    {
      "tile": {
        "sheet": 38,
        "col": 0,
        "row": 8
      },
      "x": 73,
      "y": 9
    },
    {
      "tile": {
        "sheet": 38,
        "col": 4,
        "row": 4
      },
      "x": 110,
      "y": 6
    },
    {
      "tile": {
        "sheet": 38,
        "col": 0,
        "row": 8
      },
      "x": 78,
      "y": 9
    },
    {
      "tile": {
        "sheet": 38,
        "col": 0,
        "row": 8
      },
      "x": 38,
      "y": 17
    },
    {
      "tile": {
        "sheet": 38,
        "col": 0,
        "row": 8
      },
      "x": 106,
      "y": 5
    },
    {
      "tile": {
        "sheet": 38,
        "col": 4,
        "row": 4
      },
      "x": 108,
      "y": 6
    },
    {
      "tile": {
        "sheet": 38,
        "col": 4,
        "row": 4
      },
      "x": 107,
      "y": 9
    },
    {
      "tile": {
        "sheet": 38,
        "col": 4,
        "row": 4
      },
      "x": 109,
      "y": 6
    },
    {
      "tile": {
        "sheet": 38,
        "col": 2,
        "row": 8
      },
      "x": 10,
      "y": 9
    },
    {
      "tile": {
        "sheet": 38,
        "col": 4,
        "row": 4
      },
      "x": 111,
      "y": 6
    },
    {
      "tile": {
        "sheet": 38,
        "col": 4,
        "row": 4
      },
      "x": 77,
      "y": 60
    },
    {
      "tile": {
        "sheet": 38,
        "col": 4,
        "row": 4
      },
      "x": 112,
      "y": 9
    },
    {
      "tile": {
        "sheet": 38,
        "col": 0,
        "row": 8
      },
      "x": 11,
      "y": 10
    },
    {
      "tile": {
        "sheet": 38,
        "col": 0,
        "row": 8
      },
      "x": 106,
      "y": 10
    },
    {
      "tile": {
        "sheet": 38,
        "col": 0,
        "row": 8
      },
      "x": 113,
      "y": 10
    },
    {
      "tile": {
        "sheet": 38,
        "col": 0,
        "row": 8
      },
      "x": 6,
      "y": 5
    },
    {
      "tile": {
        "sheet": 38,
        "col": 2,
        "row": 8
      },
      "x": 10,
      "y": 7
    },
    {
      "tile": {
        "sheet": 38,
        "col": 2,
        "row": 8
      },
      "x": 7,
      "y": 9
    },
    {
      "tile": {
        "sheet": 38,
        "col": 0,
        "row": 8
      },
      "x": 6,
      "y": 10
    },
    {
      "tile": {
        "sheet": 38,
        "col": 4,
        "row": 4
      },
      "x": 77,
      "y": 57
    },
    {
      "tile": {
        "sheet": 38,
        "col": 5,
        "row": 9
      },
      "x": 89,
      "y": 14
    },
    {
      "tile": {
        "sheet": 38,
        "col": 5,
        "row": 9
      },
      "x": 25,
      "y": 14
    },
    {
      "tile": {
        "sheet": 38,
        "col": 5,
        "row": 9
      },
      "x": 76,
      "y": 67
    },
    {
      "tile": {
        "sheet": 38,
        "col": 5,
        "row": 9
      },
      "x": 29,
      "y": 17
    },
    {
      "tile": {
        "sheet": 38,
        "col": 5,
        "row": 9
      },
      "x": 26,
      "y": 19
    },
    {
      "tile": {
        "sheet": 38,
        "col": 0,
        "row": 8
      },
      "x": 93,
      "y": 60
    },
    {
      "tile": {
        "sheet": 38,
        "col": 5,
        "row": 9
      },
      "x": 91,
      "y": 17
    },
    {
      "tile": {
        "sheet": 38,
        "col": 5,
        "row": 9
      },
      "x": 92,
      "y": 17
    },
    {
      "tile": {
        "sheet": 38,
        "col": 2,
        "row": 9
      },
      "x": 91,
      "y": 19
    },
    {
      "tile": {
        "sheet": 38,
        "col": 2,
        "row": 9
      },
      "x": 92,
      "y": 19
    },
    {
      "tile": {
        "sheet": 38,
        "col": 0,
        "row": 8
      },
      "x": 43,
      "y": 17
    },
    {
      "tile": {
        "sheet": 38,
        "col": 2,
        "row": 8
      },
      "x": 42,
      "y": 19
    },
    {
      "tile": {
        "sheet": 38,
        "col": 0,
        "row": 8
      },
      "x": 11,
      "y": 42
    },
    {
      "tile": {
        "sheet": 38,
        "col": 2,
        "row": 8
      },
      "x": 39,
      "y": 21
    },
    {
      "tile": {
        "sheet": 38,
        "col": 0,
        "row": 8
      },
      "x": 23,
      "y": 69
    },
    {
      "tile": {
        "sheet": 38,
        "col": 2,
        "row": 8
      },
      "x": 42,
      "y": 21
    },
    {
      "tile": {
        "sheet": 38,
        "col": 0,
        "row": 8
      },
      "x": 38,
      "y": 22
    },
    {
      "tile": {
        "sheet": 38,
        "col": 0,
        "row": 11
      },
      "x": 7,
      "y": 31
    },
    {
      "tile": {
        "sheet": 38,
        "col": 0,
        "row": 8
      },
      "x": 45,
      "y": 37
    },
    {
      "tile": {
        "sheet": 38,
        "col": 5,
        "row": 9
      },
      "x": 77,
      "y": 18
    },
    {
      "tile": {
        "sheet": 38,
        "col": 1,
        "row": 11
      },
      "x": 6,
      "y": 33
    },
    {
      "tile": {
        "sheet": 38,
        "col": 5,
        "row": 9
      },
      "x": 78,
      "y": 18
    },
    {
      "tile": {
        "sheet": 38,
        "col": 5,
        "row": 9
      },
      "x": 82,
      "y": 21
    },
    {
      "tile": {
        "sheet": 38,
        "col": 4,
        "row": 4
      },
      "x": 78,
      "y": 57
    },
    {
      "tile": {
        "sheet": 38,
        "col": 5,
        "row": 9
      },
      "x": 78,
      "y": 23
    },
    {
      "tile": {
        "sheet": 38,
        "col": 5,
        "row": 9
      },
      "x": 79,
      "y": 23
    },
    {
      "tile": {
        "sheet": 38,
        "col": 4,
        "row": 4
      },
      "x": 74,
      "y": 42
    },
    {
      "tile": {
        "sheet": 38,
        "col": 0,
        "row": 8
      },
      "x": 5,
      "y": 30
    },
    {
      "tile": {
        "sheet": 38,
        "col": 0,
        "row": 8
      },
      "x": 113,
      "y": 74
    },
    {
      "tile": {
        "sheet": 38,
        "col": 0,
        "row": 11
      },
      "x": 6,
      "y": 31
    },
    {
      "tile": {
        "sheet": 38,
        "col": 0,
        "row": 11
      },
      "x": 10,
      "y": 31
    },
    {
      "tile": {
        "sheet": 38,
        "col": 0,
        "row": 11
      },
      "x": 11,
      "y": 31
    },
    {
      "tile": {
        "sheet": 38,
        "col": 1,
        "row": 11
      },
      "x": 7,
      "y": 33
    },
    {
      "tile": {
        "sheet": 38,
        "col": 1,
        "row": 11
      },
      "x": 10,
      "y": 33
    },
    {
      "tile": {
        "sheet": 38,
        "col": 1,
        "row": 11
      },
      "x": 11,
      "y": 33
    },
    {
      "tile": {
        "sheet": 38,
        "col": 0,
        "row": 8
      },
      "x": 62,
      "y": 44
    },
    {
      "tile": {
        "sheet": 38,
        "col": 0,
        "row": 8
      },
      "x": 5,
      "y": 35
    },
    {
      "tile": {
        "sheet": 38,
        "col": 0,
        "row": 8
      },
      "x": 12,
      "y": 35
    },
    {
      "tile": {
        "sheet": 38,
        "col": 2,
        "row": 8
      },
      "x": 95,
      "y": 56
    },
    {
      "tile": {
        "sheet": 38,
        "col": 0,
        "row": 8
      },
      "x": 56,
      "y": 30
    },
    {
      "tile": {
        "sheet": 38,
        "col": 0,
        "row": 8
      },
      "x": 61,
      "y": 30
    },
    {
      "tile": {
        "sheet": 38,
        "col": 2,
        "row": 8
      },
      "x": 57,
      "y": 32
    },
    {
      "tile": {
        "sheet": 38,
        "col": 2,
        "row": 8
      },
      "x": 60,
      "y": 32
    },
    {
      "tile": {
        "sheet": 38,
        "col": 7,
        "row": 10
      },
      "x": 9,
      "y": 45
    },
    {
      "tile": {
        "sheet": 38,
        "col": 2,
        "row": 8
      },
      "x": 57,
      "y": 34
    },
    {
      "tile": {
        "sheet": 38,
        "col": 2,
        "row": 8
      },
      "x": 60,
      "y": 34
    },
    {
      "tile": {
        "sheet": 38,
        "col": 0,
        "row": 8
      },
      "x": 56,
      "y": 35
    },
    {
      "tile": {
        "sheet": 38,
        "col": 0,
        "row": 8
      },
      "x": 61,
      "y": 35
    },
    {
      "tile": {
        "sheet": 38,
        "col": 4,
        "row": 4
      },
      "x": 76,
      "y": 42
    },
    {
      "tile": {
        "sheet": 38,
        "col": 0,
        "row": 8
      },
      "x": 74,
      "y": 30
    },
    {
      "tile": {
        "sheet": 38,
        "col": 0,
        "row": 8
      },
      "x": 79,
      "y": 35
    },
    {
      "tile": {
        "sheet": 38,
        "col": 0,
        "row": 8
      },
      "x": 79,
      "y": 30
    },
    {
      "tile": {
        "sheet": 38,
        "col": 0,
        "row": 8
      },
      "x": 74,
      "y": 35
    },
    {
      "tile": {
        "sheet": 38,
        "col": 0,
        "row": 11
      },
      "x": 76,
      "y": 31
    },
    {
      "tile": {
        "sheet": 38,
        "col": 1,
        "row": 11
      },
      "x": 77,
      "y": 33
    },
    {
      "tile": {
        "sheet": 38,
        "col": 1,
        "row": 11
      },
      "x": 78,
      "y": 33
    },
    {
      "tile": {
        "sheet": 38,
        "col": 3,
        "row": 8
      },
      "x": 27,
      "y": 33
    },
    {
      "tile": {
        "sheet": 38,
        "col": 2,
        "row": 8
      },
      "x": 95,
      "y": 69
    },
    {
      "tile": {
        "sheet": 38,
        "col": 0,
        "row": 8
      },
      "x": 45,
      "y": 32
    },
    {
      "tile": {
        "sheet": 38,
        "col": 0,
        "row": 8
      },
      "x": 5,
      "y": 72
    },
    {
      "tile": {
        "sheet": 38,
        "col": 0,
        "row": 11
      },
      "x": 39,
      "y": 33
    },
    {
      "tile": {
        "sheet": 38,
        "col": 0,
        "row": 11
      },
      "x": 40,
      "y": 33
    },
    {
      "tile": {
        "sheet": 38,
        "col": 0,
        "row": 11
      },
      "x": 43,
      "y": 33
    },
    {
      "tile": {
        "sheet": 38,
        "col": 4,
        "row": 4
      },
      "x": 78,
      "y": 60
    },
    {
      "tile": {
        "sheet": 38,
        "col": 0,
        "row": 11
      },
      "x": 44,
      "y": 33
    },
    {
      "tile": {
        "sheet": 38,
        "col": 3,
        "row": 3
      },
      "x": 107,
      "y": 46
    },
    {
      "tile": {
        "sheet": 38,
        "col": 0,
        "row": 8
      },
      "x": 57,
      "y": 44
    },
    {
      "tile": {
        "sheet": 38,
        "col": 1,
        "row": 11
      },
      "x": 39,
      "y": 35
    },
    {
      "tile": {
        "sheet": 38,
        "col": 1,
        "row": 11
      },
      "x": 40,
      "y": 35
    },
    {
      "tile": {
        "sheet": 38,
        "col": 5,
        "row": 9
      },
      "x": 60,
      "y": 55
    },
    {
      "tile": {
        "sheet": 38,
        "col": 1,
        "row": 11
      },
      "x": 43,
      "y": 35
    },
    {
      "tile": {
        "sheet": 38,
        "col": 0,
        "row": 8
      },
      "x": 28,
      "y": 60
    },
    {
      "tile": {
        "sheet": 38,
        "col": 1,
        "row": 11
      },
      "x": 44,
      "y": 35
    },
    {
      "tile": {
        "sheet": 38,
        "col": 0,
        "row": 8
      },
      "x": 38,
      "y": 37
    },
    {
      "tile": {
        "sheet": 38,
        "col": 0,
        "row": 8
      },
      "x": 73,
      "y": 41
    },
    {
      "tile": {
        "sheet": 38,
        "col": 0,
        "row": 8
      },
      "x": 80,
      "y": 41
    },
    {
      "tile": {
        "sheet": 38,
        "col": 4,
        "row": 4
      },
      "x": 75,
      "y": 42
    },
    {
      "tile": {
        "sheet": 38,
        "col": 4,
        "row": 4
      },
      "x": 77,
      "y": 42
    },
    {
      "tile": {
        "sheet": 38,
        "col": 4,
        "row": 4
      },
      "x": 78,
      "y": 42
    },
    {
      "tile": {
        "sheet": 38,
        "col": 4,
        "row": 4
      },
      "x": 79,
      "y": 42
    },
    {
      "tile": {
        "sheet": 38,
        "col": 4,
        "row": 4
      },
      "x": 74,
      "y": 45
    },
    {
      "tile": {
        "sheet": 38,
        "col": 4,
        "row": 4
      },
      "x": 75,
      "y": 45
    },
    {
      "tile": {
        "sheet": 38,
        "col": 4,
        "row": 4
      },
      "x": 76,
      "y": 45
    },
    {
      "tile": {
        "sheet": 38,
        "col": 4,
        "row": 4
      },
      "x": 77,
      "y": 45
    },
    {
      "tile": {
        "sheet": 38,
        "col": 4,
        "row": 4
      },
      "x": 78,
      "y": 45
    },
    {
      "tile": {
        "sheet": 38,
        "col": 4,
        "row": 4
      },
      "x": 79,
      "y": 45
    },
    {
      "tile": {
        "sheet": 38,
        "col": 0,
        "row": 8
      },
      "x": 73,
      "y": 46
    },
    {
      "tile": {
        "sheet": 38,
        "col": 0,
        "row": 8
      },
      "x": 62,
      "y": 49
    },
    {
      "tile": {
        "sheet": 38,
        "col": 0,
        "row": 8
      },
      "x": 11,
      "y": 60
    },
    {
      "tile": {
        "sheet": 38,
        "col": 0,
        "row": 8
      },
      "x": 80,
      "y": 46
    },
    {
      "tile": {
        "sheet": 38,
        "col": 2,
        "row": 8
      },
      "x": 7,
      "y": 43
    },
    {
      "tile": {
        "sheet": 38,
        "col": 2,
        "row": 8
      },
      "x": 8,
      "y": 43
    },
    {
      "tile": {
        "sheet": 38,
        "col": 2,
        "row": 8
      },
      "x": 10,
      "y": 43
    },
    {
      "tile": {
        "sheet": 38,
        "col": 0,
        "row": 8
      },
      "x": 6,
      "y": 55
    },
    {
      "tile": {
        "sheet": 38,
        "col": 0,
        "row": 8
      },
      "x": 81,
      "y": 56
    },
    {
      "tile": {
        "sheet": 38,
        "col": 6,
        "row": 10
      },
      "x": 8,
      "y": 45
    },
    {
      "tile": {
        "sheet": 38,
        "col": 0,
        "row": 8
      },
      "x": 6,
      "y": 47
    },
    {
      "tile": {
        "sheet": 38,
        "col": 0,
        "row": 8
      },
      "x": 90,
      "y": 42
    },
    {
      "tile": {
        "sheet": 38,
        "col": 0,
        "row": 8
      },
      "x": 97,
      "y": 42
    },
    {
      "tile": {
        "sheet": 38,
        "col": 0,
        "row": 3
      },
      "x": 91,
      "y": 43
    },
    {
      "tile": {
        "sheet": 38,
        "col": 0,
        "row": 3
      },
      "x": 92,
      "y": 43
    },
    {
      "tile": {
        "sheet": 38,
        "col": 3,
        "row": 3
      },
      "x": 95,
      "y": 43
    },
    {
      "tile": {
        "sheet": 38,
        "col": 3,
        "row": 3
      },
      "x": 96,
      "y": 43
    },
    {
      "tile": {
        "sheet": 38,
        "col": 2,
        "row": 8
      },
      "x": 92,
      "y": 71
    },
    {
      "tile": {
        "sheet": 38,
        "col": 5,
        "row": 3
      },
      "x": 91,
      "y": 46
    },
    {
      "tile": {
        "sheet": 38,
        "col": 0,
        "row": 3
      },
      "x": 105,
      "y": 44
    },
    {
      "tile": {
        "sheet": 38,
        "col": 5,
        "row": 3
      },
      "x": 92,
      "y": 46
    },
    {
      "tile": {
        "sheet": 38,
        "col": 1,
        "row": 3
      },
      "x": 95,
      "y": 46
    },
    {
      "tile": {
        "sheet": 38,
        "col": 2,
        "row": 8
      },
      "x": 25,
      "y": 56
    },
    {
      "tile": {
        "sheet": 38,
        "col": 1,
        "row": 3
      },
      "x": 96,
      "y": 46
    },
    {
      "tile": {
        "sheet": 38,
        "col": 0,
        "row": 8
      },
      "x": 90,
      "y": 47
    },
    {
      "tile": {
        "sheet": 38,
        "col": 0,
        "row": 8
      },
      "x": 103,
      "y": 43
    },
    {
      "tile": {
        "sheet": 38,
        "col": 0,
        "row": 8
      },
      "x": 108,
      "y": 43
    },
    {
      "tile": {
        "sheet": 38,
        "col": 0,
        "row": 3
      },
      "x": 104,
      "y": 44
    },
    {
      "tile": {
        "sheet": 38,
        "col": 3,
        "row": 3
      },
      "x": 106,
      "y": 46
    },
    {
      "tile": {
        "sheet": 38,
        "col": 0,
        "row": 8
      },
      "x": 103,
      "y": 48
    },
    {
      "tile": {
        "sheet": 38,
        "col": 0,
        "row": 8
      },
      "x": 108,
      "y": 48
    },
    {
      "tile": {
        "sheet": 38,
        "col": 0,
        "row": 3
      },
      "x": 58,
      "y": 45
    },
    {
      "tile": {
        "sheet": 38,
        "col": 0,
        "row": 3
      },
      "x": 25,
      "y": 70
    },
    {
      "tile": {
        "sheet": 38,
        "col": 0,
        "row": 3
      },
      "x": 59,
      "y": 45
    },
    {
      "tile": {
        "sheet": 38,
        "col": 3,
        "row": 3
      },
      "x": 60,
      "y": 47
    },
    {
      "tile": {
        "sheet": 38,
        "col": 3,
        "row": 3
      },
      "x": 61,
      "y": 47
    },
    {
      "tile": {
        "sheet": 38,
        "col": 0,
        "row": 8
      },
      "x": 57,
      "y": 49
    },
    {
      "tile": {
        "sheet": 38,
        "col": 0,
        "row": 8
      },
      "x": 108,
      "y": 54
    },
    {
      "tile": {
        "sheet": 38,
        "col": 0,
        "row": 8
      },
      "x": 113,
      "y": 54
    },
    {
      "tile": {
        "sheet": 38,
        "col": 0,
        "row": 8
      },
      "x": 108,
      "y": 59
    },
    {
      "tile": {
        "sheet": 38,
        "col": 0,
        "row": 8
      },
      "x": 113,
      "y": 59
    },
    {
      "tile": {
        "sheet": 38,
        "col": 0,
        "row": 8
      },
      "x": 23,
      "y": 55
    },
    {
      "tile": {
        "sheet": 38,
        "col": 0,
        "row": 8
      },
      "x": 28,
      "y": 55
    },
    {
      "tile": {
        "sheet": 38,
        "col": 2,
        "row": 8
      },
      "x": 24,
      "y": 56
    },
    {
      "tile": {
        "sheet": 38,
        "col": 2,
        "row": 8
      },
      "x": 27,
      "y": 56
    },
    {
      "tile": {
        "sheet": 38,
        "col": 2,
        "row": 8
      },
      "x": 28,
      "y": 56
    },
    {
      "tile": {
        "sheet": 38,
        "col": 6,
        "row": 10
      },
      "x": 25,
      "y": 58
    },
    {
      "tile": {
        "sheet": 38,
        "col": 3,
        "row": 3
      },
      "x": 27,
      "y": 72
    },
    {
      "tile": {
        "sheet": 38,
        "col": 7,
        "row": 10
      },
      "x": 26,
      "y": 58
    },
    {
      "tile": {
        "sheet": 38,
        "col": 0,
        "row": 8
      },
      "x": 23,
      "y": 60
    },
    {
      "tile": {
        "sheet": 38,
        "col": 5,
        "row": 9
      },
      "x": 65,
      "y": 58
    },
    {
      "tile": {
        "sheet": 38,
        "col": 5,
        "row": 9
      },
      "x": 61,
      "y": 55
    },
    {
      "tile": {
        "sheet": 38,
        "col": 5,
        "row": 9
      },
      "x": 61,
      "y": 60
    },
    {
      "tile": {
        "sheet": 38,
        "col": 5,
        "row": 9
      },
      "x": 62,
      "y": 60
    },
    {
      "tile": {
        "sheet": 38,
        "col": 0,
        "row": 8
      },
      "x": 11,
      "y": 55
    },
    {
      "tile": {
        "sheet": 38,
        "col": 0,
        "row": 8
      },
      "x": 6,
      "y": 60
    },
    {
      "tile": {
        "sheet": 38,
        "col": 0,
        "row": 8
      },
      "x": 93,
      "y": 55
    },
    {
      "tile": {
        "sheet": 38,
        "col": 0,
        "row": 8
      },
      "x": 98,
      "y": 55
    },
    {
      "tile": {
        "sheet": 38,
        "col": 2,
        "row": 8
      },
      "x": 94,
      "y": 56
    },
    {
      "tile": {
        "sheet": 38,
        "col": 2,
        "row": 8
      },
      "x": 97,
      "y": 56
    },
    {
      "tile": {
        "sheet": 38,
        "col": 2,
        "row": 8
      },
      "x": 98,
      "y": 56
    },
    {
      "tile": {
        "sheet": 38,
        "col": 6,
        "row": 10
      },
      "x": 95,
      "y": 58
    },
    {
      "tile": {
        "sheet": 38,
        "col": 7,
        "row": 10
      },
      "x": 96,
      "y": 58
    },
    {
      "tile": {
        "sheet": 38,
        "col": 0,
        "row": 8
      },
      "x": 98,
      "y": 60
    },
    {
      "tile": {
        "sheet": 38,
        "col": 0,
        "row": 8
      },
      "x": 76,
      "y": 56
    },
    {
      "tile": {
        "sheet": 38,
        "col": 4,
        "row": 4
      },
      "x": 79,
      "y": 57
    },
    {
      "tile": {
        "sheet": 38,
        "col": 4,
        "row": 4
      },
      "x": 80,
      "y": 57
    },
    {
      "tile": {
        "sheet": 38,
        "col": 4,
        "row": 4
      },
      "x": 79,
      "y": 60
    },
    {
      "tile": {
        "sheet": 38,
        "col": 0,
        "row": 8
      },
      "x": 76,
      "y": 61
    },
    {
      "tile": {
        "sheet": 38,
        "col": 0,
        "row": 8
      },
      "x": 81,
      "y": 61
    },
    {
      "tile": {
        "sheet": 38,
        "col": 0,
        "row": 8
      },
      "x": 5,
      "y": 67
    },
    {
      "tile": {
        "sheet": 38,
        "col": 0,
        "row": 8
      },
      "x": 10,
      "y": 67
    },
    {
      "tile": {
        "sheet": 38,
        "col": 5,
        "row": 9
      },
      "x": 77,
      "y": 67
    },
    {
      "tile": {
        "sheet": 38,
        "col": 5,
        "row": 9
      },
      "x": 81,
      "y": 70
    },
    {
      "tile": {
        "sheet": 38,
        "col": 5,
        "row": 9
      },
      "x": 77,
      "y": 72
    },
    {
      "tile": {
        "sheet": 38,
        "col": 5,
        "row": 9
      },
      "x": 78,
      "y": 72
    },
    {
      "tile": {
        "sheet": 38,
        "col": 0,
        "row": 8
      },
      "x": 28,
      "y": 74
    },
    {
      "tile": {
        "sheet": 38,
        "col": 0,
        "row": 8
      },
      "x": 91,
      "y": 67
    },
    {
      "tile": {
        "sheet": 38,
        "col": 0,
        "row": 8
      },
      "x": 96,
      "y": 67
    },
    {
      "tile": {
        "sheet": 38,
        "col": 2,
        "row": 8
      },
      "x": 92,
      "y": 69
    },
    {
      "tile": {
        "sheet": 38,
        "col": 2,
        "row": 8
      },
      "x": 95,
      "y": 71
    },
    {
      "tile": {
        "sheet": 38,
        "col": 0,
        "row": 8
      },
      "x": 91,
      "y": 72
    },
    {
      "tile": {
        "sheet": 38,
        "col": 0,
        "row": 8
      },
      "x": 96,
      "y": 72
    },
    {
      "tile": {
        "sheet": 38,
        "col": 0,
        "row": 8
      },
      "x": 28,
      "y": 69
    },
    {
      "tile": {
        "sheet": 38,
        "col": 0,
        "row": 3
      },
      "x": 24,
      "y": 70
    },
    {
      "tile": {
        "sheet": 38,
        "col": 3,
        "row": 3
      },
      "x": 26,
      "y": 72
    },
    {
      "tile": {
        "sheet": 38,
        "col": 0,
        "row": 8
      },
      "x": 23,
      "y": 74
    },
    {
      "tile": {
        "sheet": 38,
        "col": 0,
        "row": 8
      },
      "x": 108,
      "y": 69
    },
    {
      "tile": {
        "sheet": 38,
        "col": 0,
        "row": 8
      },
      "x": 113,
      "y": 69
    },
    {
      "tile": {
        "sheet": 38,
        "col": 0,
        "row": 8
      },
      "x": 108,
      "y": 74
    }
  ],
  "_last_saved": "1418819254_1"
}